{
    "data": [
        {
            "id":1,
            "url":"https://youimg1.c-ctrip.com/target/0106x120008ghpc63B032_D_300_240_Q90.jpg?proc=autoorient",
            "text":"十大正宗本帮菜"
        },
        {
            "id":2,
            "url":"https://youimg1.c-ctrip.com/target/0103f120009zier8f2B77_D_300_240_Q90.jpg?proc=autoorient",
            "text":"特色风味小吃"
        },
        {
            "id":3,
            "url":"https://youimg1.c-ctrip.com/target/0104012000a25ettw305C_D_300_240_Q90.jpg?proc=autoorient",
            "text":"外滩风情餐厅"
        },
        {
            "id":4,
            "url":"https://youimg1.c-ctrip.com/target/0103u120009e1k6hgD4C4_D_300_240_Q90.jpg?proc=autoorient",
            "text":"舌尖上的糕团"
        },
        {
            "id":5,
            "url":"https://youimg1.c-ctrip.com/target/0103c12000a9zoby6EBAC_D_300_240_Q90.jpg?proc=autoorient",
            "text":"深夜居酒屋"
        },
        {
            "id":6,
            "url":"https://youimg1.c-ctrip.com/target/0102c12000a9zj6we7B5E_D_300_240_Q90.jpg?proc=autoorient",
            "text":"魔都Bistro指南"
        },
        {
            "id":7,
            "url":"https://youimg1.c-ctrip.com/target/0102d12000a9z5v3zC8B7_D_300_240_Q90.jpg?proc=autoorient",
            "text":"魔都深夜食堂"
        },
        {
            "id":8,
            "url":"https://youimg1.c-ctrip.com/target/0101o12000a6d0k95455F_D_300_240_Q90.jpg?proc=autoorient",
            "text":"微醺酒馆餐吧"
        }
    ]
}