{
	"data": {
		"1":{
			"id": 1,
			"imgs": [
				"https://youimg1.c-ctrip.com/target/10030q000000goy0v1E89_D_750_562_Q90.jpg?proc=autoorient",
				"https://youimg1.c-ctrip.com/target/10090q000000gc0wr3753_D_750_562_Q90.jpg?proc=autoorient",
				"https://youimg1.c-ctrip.com/target/100l0q000000gndqr589A_D_750_562_Q90.jpg?proc=autoorient"
			],
			"name": "红盔甲",
			"score": 3.1,
			"reviews": 201,
			"avgPrice": 521,
			"exactPosition": "天钥桥路333号",
			"generalPosition": "淮海路/新天地地区",
			"style": "小龙虾",
			"duration": [
				[
					11,
					13.5
				],
				[
					17,
					21
				]
			],
			"tel": "16742244272",
			"distance": 6765,
			"video": "https://ak-v.tripcdn.com/videos/1A091t000001i1av39C52.mp4?ts=1622898856678"
		},
		"2":{
			"id": 2,
			"imgs": [
				"https://youimg1.c-ctrip.com/target/10030q000000goy0v1E89_D_750_562_Q90.jpg?proc=autoorient",
				"https://youimg1.c-ctrip.com/target/10090q000000gc0wr3753_D_750_562_Q90.jpg?proc=autoorient",
				"https://youimg1.c-ctrip.com/target/100l0q000000gndqr589A_D_750_562_Q90.jpg?proc=autoorient"
			],
			"name": "新辣道鱼火锅",
			"score": 4.3,
			"reviews": 982,
			"avgPrice": 468,
			"exactPosition": "天钥桥路580号星游城4层409A",
			"generalPosition": "淮海路/新天地地区",
			"style": "鱼火锅",
			"duration": [
				[
					11,
					13.5
				],
				[
					17,
					21
				]
			],
			"tel": "13642131157",
			"distance": 8588,
			"video": "https://ak-v.tripcdn.com/videos/1A091t000001i1av39C52.mp4?ts=1622898856678"
		},
		"3":{
			"id": 3,
			"imgs": [
				"https://youimg1.c-ctrip.com/target/10030q000000goy0v1E89_D_750_562_Q90.jpg?proc=autoorient",
				"https://youimg1.c-ctrip.com/target/10090q000000gc0wr3753_D_750_562_Q90.jpg?proc=autoorient",
				"https://youimg1.c-ctrip.com/target/100l0q000000gndqr589A_D_750_562_Q90.jpg?proc=autoorient"
			],
			"name": "阿娘面",
			"score": 4.8,
			"reviews": 627,
			"avgPrice": 424,
			"exactPosition": "卢湾区思南路36号2",
			"generalPosition": "淮海路/新天地地区",
			"style": "面食",
			"duration": [
				[
					11,
					13.5
				],
				[
					17,
					21
				]
			],
			"tel": "15121213567",
			"distance": 4463,
			"video": "https://ak-v.tripcdn.com/videos/1A091t000001i1av39C52.mp4?ts=1622898856678"
		},
		"4":{
			"id": 4,
			"imgs": [
				"https://youimg1.c-ctrip.com/target/10030q000000goy0v1E89_D_750_562_Q90.jpg?proc=autoorient",
				"https://youimg1.c-ctrip.com/target/10090q000000gc0wr3753_D_750_562_Q90.jpg?proc=autoorient",
				"https://youimg1.c-ctrip.com/target/100l0q000000gndqr589A_D_750_562_Q90.jpg?proc=autoorient"
			],
			"name": "真田食堂(静安店)",
			"score": 3.5,
			"reviews": 819,
			"avgPrice": 353,
			"exactPosition": "奉贤路288号2楼",
			"generalPosition": "淮海路/新天地地区",
			"style": "居酒屋",
			"duration": [
				[
					11,
					13.5
				],
				[
					17,
					21
				]
			],
			"tel": "13245744168",
			"distance": 9603,
			"video": "https://ak-v.tripcdn.com/videos/1A091t000001i1av39C52.mp4?ts=1622898856678"
		},
		"5":{
			"id": 5,
			"imgs": [
				"https://youimg1.c-ctrip.com/target/10030q000000goy0v1E89_D_750_562_Q90.jpg?proc=autoorient",
				"https://youimg1.c-ctrip.com/target/10090q000000gc0wr3753_D_750_562_Q90.jpg?proc=autoorient",
				"https://youimg1.c-ctrip.com/target/100l0q000000gndqr589A_D_750_562_Q90.jpg?proc=autoorient"
			],
			"name": "新荣记",
			"score": 4.9,
			"reviews": 192,
			"avgPrice": 694,
			"exactPosition": "淮海中路138号上海广场5楼503商铺",
			"generalPosition": "淮海路/新天地地区",
			"style": "江浙菜",
			"duration": [
				[
					11,
					13.5
				],
				[
					17,
					21
				]
			],
			"tel": "17241226730",
			"distance": 1680,
			"video": "https://ak-v.tripcdn.com/videos/1A091t000001i1av39C52.mp4?ts=1622898856678"
		},
		"6":{
			"id": 6,
			"imgs": [
				"https://youimg1.c-ctrip.com/target/10030q000000goy0v1E89_D_750_562_Q90.jpg?proc=autoorient",
				"https://youimg1.c-ctrip.com/target/10090q000000gc0wr3753_D_750_562_Q90.jpg?proc=autoorient",
				"https://youimg1.c-ctrip.com/target/100l0q000000gndqr589A_D_750_562_Q90.jpg?proc=autoorient"
			],
			"name": "老地方面馆",
			"score": 4.4,
			"reviews": 791,
			"avgPrice": 751,
			"exactPosition": "徐汇区襄阳南路233号",
			"generalPosition": "淮海路/新天地地区",
			"style": "面食",
			"duration": [
				[
					11,
					13.5
				],
				[
					17,
					21
				]
			],
			"tel": "14104815196",
			"distance": 1906,
			"video": "https://ak-v.tripcdn.com/videos/1A091t000001i1av39C52.mp4?ts=1622898856678"
		},
		"7":{
			"id": 7,
			"imgs": [
				"https://youimg1.c-ctrip.com/target/10030q000000goy0v1E89_D_750_562_Q90.jpg?proc=autoorient",
				"https://youimg1.c-ctrip.com/target/10090q000000gc0wr3753_D_750_562_Q90.jpg?proc=autoorient",
				"https://youimg1.c-ctrip.com/target/100l0q000000gndqr589A_D_750_562_Q90.jpg?proc=autoorient"
			],
			"name": "老娘舅快捷餐厅",
			"score": 4.5,
			"reviews": 535,
			"avgPrice": 268,
			"exactPosition": "淮海中路988-1临",
			"generalPosition": "淮海路/新天地地区",
			"style": "中式快餐",
			"duration": [
				[
					11,
					13.5
				],
				[
					17,
					21
				]
			],
			"tel": "16092379478",
			"distance": 3997,
			"video": "https://ak-v.tripcdn.com/videos/1A091t000001i1av39C52.mp4?ts=1622898856678"
		},
		"8":{
			"id": 8,
			"imgs": [
				"https://youimg1.c-ctrip.com/target/10030q000000goy0v1E89_D_750_562_Q90.jpg?proc=autoorient",
				"https://youimg1.c-ctrip.com/target/10090q000000gc0wr3753_D_750_562_Q90.jpg?proc=autoorient",
				"https://youimg1.c-ctrip.com/target/100l0q000000gndqr589A_D_750_562_Q90.jpg?proc=autoorient"
			],
			"name": "孔雀川菜(新天地店)",
			"score": 4.2,
			"reviews": 313,
			"avgPrice": 160,
			"exactPosition": "太仓路181弄新天地北里235号02单元",
			"generalPosition": "淮海路/新天地地区",
			"style": "川菜",
			"duration": [
				[
					11,
					13.5
				],
				[
					17,
					21
				]
			],
			"tel": "18170607623",
			"distance": 427,
			"video": "https://ak-v.tripcdn.com/videos/1A091t000001i1av39C52.mp4?ts=1622898856678"
		},
		"9":{
			"id": 9,
			"imgs": [
				"https://youimg1.c-ctrip.com/target/10030q000000goy0v1E89_D_750_562_Q90.jpg?proc=autoorient",
				"https://youimg1.c-ctrip.com/target/10090q000000gc0wr3753_D_750_562_Q90.jpg?proc=autoorient",
				"https://youimg1.c-ctrip.com/target/100l0q000000gndqr589A_D_750_562_Q90.jpg?proc=autoorient"
			],
			"name": "Bella Napoli",
			"score": 4.1,
			"reviews": 614,
			"avgPrice": 341,
			"exactPosition": "南汇路73号",
			"generalPosition": "淮海路/新天地地区",
			"style": "披萨",
			"duration": [
				[
					11,
					13.5
				],
				[
					17,
					21
				]
			],
			"tel": "15871442118",
			"distance": 5620,
			"video": "https://ak-v.tripcdn.com/videos/1A091t000001i1av39C52.mp4?ts=1622898856678"
		},
		"10":{
			"id": 10,
			"imgs": [
				"https://youimg1.c-ctrip.com/target/10030q000000goy0v1E89_D_750_562_Q90.jpg?proc=autoorient",
				"https://youimg1.c-ctrip.com/target/10090q000000gc0wr3753_D_750_562_Q90.jpg?proc=autoorient",
				"https://youimg1.c-ctrip.com/target/100l0q000000gndqr589A_D_750_562_Q90.jpg?proc=autoorient"
			],
			"name": "重庆高老九火锅",
			"score": 4.5,
			"reviews": 534,
			"avgPrice": 953,
			"exactPosition": "上海市杨浦区唐山路1018号宝地广场F2",
			"generalPosition": "淮海路/新天地地区",
			"style": "重庆火锅",
			"duration": [
				[
					11,
					13.5
				],
				[
					17,
					21
				]
			],
			"tel": "18944645613",
			"distance": 1985,
			"video": "https://ak-v.tripcdn.com/videos/1A091t000001i1av39C52.mp4?ts=1622898856678"
		},
		"11":{
			"id": 11,
			"imgs": [
				"https://youimg1.c-ctrip.com/target/10030q000000goy0v1E89_D_750_562_Q90.jpg?proc=autoorient",
				"https://youimg1.c-ctrip.com/target/10090q000000gc0wr3753_D_750_562_Q90.jpg?proc=autoorient",
				"https://youimg1.c-ctrip.com/target/100l0q000000gndqr589A_D_750_562_Q90.jpg?proc=autoorient"
			],
			"name": "沪小胖",
			"score": 3.4,
			"reviews": 41,
			"avgPrice": 281,
			"exactPosition": "淮海中路438号2楼",
			"generalPosition": "淮海路/新天地地区",
			"style": "小龙虾",
			"duration": [
				[
					11,
					13.5
				],
				[
					17,
					21
				]
			],
			"tel": "13175678044",
			"distance": 8357,
			"video": "https://ak-v.tripcdn.com/videos/1A091t000001i1av39C52.mp4?ts=1622898856678"
		},
		"12":{
			"id": 12,
			"imgs": [
				"https://youimg1.c-ctrip.com/target/10030q000000goy0v1E89_D_750_562_Q90.jpg?proc=autoorient",
				"https://youimg1.c-ctrip.com/target/10090q000000gc0wr3753_D_750_562_Q90.jpg?proc=autoorient",
				"https://youimg1.c-ctrip.com/target/100l0q000000gndqr589A_D_750_562_Q90.jpg?proc=autoorient"
			],
			"name": "Joe's Pizza",
			"score": 4.7,
			"reviews": 835,
			"avgPrice": 668,
			"exactPosition": "南京西路1788号梅龙镇广场B1楼",
			"generalPosition": "淮海路/新天地地区",
			"style": "披萨",
			"duration": [
				[
					11,
					13.5
				],
				[
					17,
					21
				]
			],
			"tel": "18446146326",
			"distance": 692,
			"video": "https://ak-v.tripcdn.com/videos/1A091t000001i1av39C52.mp4?ts=1622898856678"
		},
		"13":{
			"id": 13,
			"imgs": [
				"https://youimg1.c-ctrip.com/target/10030q000000goy0v1E89_D_750_562_Q90.jpg?proc=autoorient",
				"https://youimg1.c-ctrip.com/target/10090q000000gc0wr3753_D_750_562_Q90.jpg?proc=autoorient",
				"https://youimg1.c-ctrip.com/target/100l0q000000gndqr589A_D_750_562_Q90.jpg?proc=autoorient"
			],
			"name": "麦当劳",
			"score": 4.5,
			"reviews": 767,
			"avgPrice": 828,
			"exactPosition": "浦江镇新浜路555号万达广场1楼",
			"generalPosition": "淮海路/新天地地区",
			"style": "西式快餐",
			"duration": [
				[
					11,
					13.5
				],
				[
					17,
					21
				]
			],
			"tel": "18521695542",
			"distance": 3176,
			"video": "https://ak-v.tripcdn.com/videos/1A091t000001i1av39C52.mp4?ts=1622898856678"
		},
		"14":{
			"id": 14,
			"imgs": [
				"https://youimg1.c-ctrip.com/target/10030q000000goy0v1E89_D_750_562_Q90.jpg?proc=autoorient",
				"https://youimg1.c-ctrip.com/target/10090q000000gc0wr3753_D_750_562_Q90.jpg?proc=autoorient",
				"https://youimg1.c-ctrip.com/target/100l0q000000gndqr589A_D_750_562_Q90.jpg?proc=autoorient"
			],
			"name": "争鲜回转寿司",
			"score": 4.3,
			"reviews": 543,
			"avgPrice": 817,
			"exactPosition": "黄浦区福州路567号1楼",
			"generalPosition": "淮海路/新天地地区",
			"style": "寿司",
			"duration": [
				[
					11,
					13.5
				],
				[
					17,
					21
				]
			],
			"tel": "13217813282",
			"distance": 7208,
			"video": "https://ak-v.tripcdn.com/videos/1A091t000001i1av39C52.mp4?ts=1622898856678"
		},
		"15":{
			"id": 15,
			"imgs": [
				"https://youimg1.c-ctrip.com/target/10030q000000goy0v1E89_D_750_562_Q90.jpg?proc=autoorient",
				"https://youimg1.c-ctrip.com/target/10090q000000gc0wr3753_D_750_562_Q90.jpg?proc=autoorient",
				"https://youimg1.c-ctrip.com/target/100l0q000000gndqr589A_D_750_562_Q90.jpg?proc=autoorient"
			],
			"name": "坎爷秘制火锅",
			"score": 3.8,
			"reviews": 945,
			"avgPrice": 448,
			"exactPosition": "打浦路11号",
			"generalPosition": "淮海路/新天地地区",
			"style": "重庆火锅",
			"duration": [
				[
					11,
					13.5
				],
				[
					17,
					21
				]
			],
			"tel": "16831446837",
			"distance": 3342,
			"video": "https://ak-v.tripcdn.com/videos/1A091t000001i1av39C52.mp4?ts=1622898856678"
		},
		"16":{
			"id": 16,
			"imgs": [
				"https://youimg1.c-ctrip.com/target/10030q000000goy0v1E89_D_750_562_Q90.jpg?proc=autoorient",
				"https://youimg1.c-ctrip.com/target/10090q000000gc0wr3753_D_750_562_Q90.jpg?proc=autoorient",
				"https://youimg1.c-ctrip.com/target/100l0q000000gndqr589A_D_750_562_Q90.jpg?proc=autoorient"
			],
			"name": "巡湘记",
			"score": 4.5,
			"reviews": 855,
			"avgPrice": 167,
			"exactPosition": "黄浦区南京东路829号上海世茂广场F5",
			"generalPosition": "淮海路/新天地地区",
			"style": "湘菜",
			"duration": [
				[
					11,
					13.5
				],
				[
					17,
					21
				]
			],
			"tel": "14639267534",
			"distance": 84,
			"video": "https://ak-v.tripcdn.com/videos/1A091t000001i1av39C52.mp4?ts=1622898856678"
		},
		"17":{
			"id": 17,
			"imgs": [
				"https://youimg1.c-ctrip.com/target/10030q000000goy0v1E89_D_750_562_Q90.jpg?proc=autoorient",
				"https://youimg1.c-ctrip.com/target/10090q000000gc0wr3753_D_750_562_Q90.jpg?proc=autoorient",
				"https://youimg1.c-ctrip.com/target/100l0q000000gndqr589A_D_750_562_Q90.jpg?proc=autoorient"
			],
			"name": "点都德",
			"score": 3.6,
			"reviews": 171,
			"avgPrice": 255,
			"exactPosition": "黄浦区黄陂南路838弄中海环宇荟B1",
			"generalPosition": "淮海路/新天地地区",
			"style": "粤菜",
			"duration": [
				[
					11,
					13.5
				],
				[
					17,
					21
				]
			],
			"tel": "17962367123",
			"distance": 1046,
			"video": "https://ak-v.tripcdn.com/videos/1A091t000001i1av39C52.mp4?ts=1622898856678"
		},
		"18":{
			"id": 18,
			"imgs": [
				"https://youimg1.c-ctrip.com/target/10030q000000goy0v1E89_D_750_562_Q90.jpg?proc=autoorient",
				"https://youimg1.c-ctrip.com/target/10090q000000gc0wr3753_D_750_562_Q90.jpg?proc=autoorient",
				"https://youimg1.c-ctrip.com/target/100l0q000000gndqr589A_D_750_562_Q90.jpg?proc=autoorient"
			],
			"name": "哎呀堡",
			"score": 4.6,
			"reviews": 816,
			"avgPrice": 337,
			"exactPosition": "黄浦区淮海中路333号香港广场南座B1楼",
			"generalPosition": "淮海路/新天地地区",
			"style": "西式快餐",
			"duration": [
				[
					11,
					13.5
				],
				[
					17,
					21
				]
			],
			"tel": "17975733633",
			"distance": 4111,
			"video": "https://ak-v.tripcdn.com/videos/1A091t000001i1av39C52.mp4?ts=1622898856678"
		},
		"19":{
			"id": 19,
			"imgs": [
				"https://youimg1.c-ctrip.com/target/10030q000000goy0v1E89_D_750_562_Q90.jpg?proc=autoorient",
				"https://youimg1.c-ctrip.com/target/10090q000000gc0wr3753_D_750_562_Q90.jpg?proc=autoorient",
				"https://youimg1.c-ctrip.com/target/100l0q000000gndqr589A_D_750_562_Q90.jpg?proc=autoorient"
			],
			"name": "萨莉亚意式餐厅",
			"score": 4.6,
			"reviews": 473,
			"avgPrice": 995,
			"exactPosition": "黄浦区南京东路353号悦荟mosaicF6",
			"generalPosition": "淮海路/新天地地区",
			"style": "意大利菜",
			"duration": [
				[
					11,
					13.5
				],
				[
					17,
					21
				]
			],
			"tel": "15855868145",
			"distance": 4786,
			"video": "https://ak-v.tripcdn.com/videos/1A091t000001i1av39C52.mp4?ts=1622898856678"
		},
		"20":{
			"id": 20,
			"imgs": [
				"https://youimg1.c-ctrip.com/target/10030q000000goy0v1E89_D_750_562_Q90.jpg?proc=autoorient",
				"https://youimg1.c-ctrip.com/target/10090q000000gc0wr3753_D_750_562_Q90.jpg?proc=autoorient",
				"https://youimg1.c-ctrip.com/target/100l0q000000gndqr589A_D_750_562_Q90.jpg?proc=autoorient"
			],
			"name": "三姐米粉王",
			"score": 4.4,
			"reviews": 146,
			"avgPrice": 584,
			"exactPosition": "黄浦区肇嘉浜路16号",
			"generalPosition": "淮海路/新天地地区",
			"style": "米粉/米线",
			"duration": [
				[
					11,
					13.5
				],
				[
					17,
					21
				]
			],
			"tel": "17352148814",
			"distance": 9257,
			"video": "https://ak-v.tripcdn.com/videos/1A091t000001i1av39C52.mp4?ts=1622898856678"
		},
		"21":{
			"id": 21,
			"imgs": [
				"https://youimg1.c-ctrip.com/target/10030q000000goy0v1E89_D_750_562_Q90.jpg?proc=autoorient",
				"https://youimg1.c-ctrip.com/target/10090q000000gc0wr3753_D_750_562_Q90.jpg?proc=autoorient",
				"https://youimg1.c-ctrip.com/target/100l0q000000gndqr589A_D_750_562_Q90.jpg?proc=autoorient"
			],
			"name": "老北京火锅",
			"score": 4.9,
			"reviews": 734,
			"avgPrice": 161,
			"exactPosition": "嘉定区嘉峪关路280弄10号",
			"generalPosition": "淮海路/新天地地区",
			"style": "老北京火锅",
			"duration": [
				[
					11,
					13.5
				],
				[
					17,
					21
				]
			],
			"tel": "18832498552",
			"distance": 4950,
			"video": "https://ak-v.tripcdn.com/videos/1A091t000001i1av39C52.mp4?ts=1622898856678"
		},
		"22":{
			"id": 22,
			"imgs": [
				"https://youimg1.c-ctrip.com/target/10030q000000goy0v1E89_D_750_562_Q90.jpg?proc=autoorient",
				"https://youimg1.c-ctrip.com/target/10090q000000gc0wr3753_D_750_562_Q90.jpg?proc=autoorient",
				"https://youimg1.c-ctrip.com/target/100l0q000000gndqr589A_D_750_562_Q90.jpg?proc=autoorient"
			],
			"name": "Jean Georges",
			"score": 4.3,
			"reviews": 464,
			"avgPrice": 916,
			"exactPosition": "黄浦区中山东一路3号外滩3号4层",
			"generalPosition": "淮海路/新天地地区",
			"style": "法国菜",
			"duration": [
				[
					11,
					13.5
				],
				[
					17,
					21
				]
			],
			"tel": "15222780116",
			"distance": 6449,
			"video": "https://ak-v.tripcdn.com/videos/1A091t000001i1av39C52.mp4?ts=1622898856678"
		},
		"23":{
			"id": 23,
			"imgs": [
				"https://youimg1.c-ctrip.com/target/10030q000000goy0v1E89_D_750_562_Q90.jpg?proc=autoorient",
				"https://youimg1.c-ctrip.com/target/10090q000000gc0wr3753_D_750_562_Q90.jpg?proc=autoorient",
				"https://youimg1.c-ctrip.com/target/100l0q000000gndqr589A_D_750_562_Q90.jpg?proc=autoorient"
			],
			"name": "鸟安(中山公园店)",
			"score": 3.3,
			"reviews": 789,
			"avgPrice": 541,
			"exactPosition": "长宁区安化路99号2楼",
			"generalPosition": "淮海路/新天地地区",
			"style": "居酒屋",
			"duration": [
				[
					11,
					13.5
				],
				[
					17,
					21
				]
			],
			"tel": "18197141475",
			"distance": 7716,
			"video": "https://ak-v.tripcdn.com/videos/1A091t000001i1av39C52.mp4?ts=1622898856678"
		},
		"24":{
			"id": 24,
			"imgs": [
				"https://youimg1.c-ctrip.com/target/10030q000000goy0v1E89_D_750_562_Q90.jpg?proc=autoorient",
				"https://youimg1.c-ctrip.com/target/10090q000000gc0wr3753_D_750_562_Q90.jpg?proc=autoorient",
				"https://youimg1.c-ctrip.com/target/100l0q000000gndqr589A_D_750_562_Q90.jpg?proc=autoorient"
			],
			"name": "香港龙凤楼",
			"score": 3.4,
			"reviews": 832,
			"avgPrice": 496,
			"exactPosition": "静安区巨鹿路889弄",
			"generalPosition": "淮海路/新天地地区",
			"style": "粤菜",
			"duration": [
				[
					11,
					13.5
				],
				[
					17,
					21
				]
			],
			"tel": "19478764228",
			"distance": 6561,
			"video": "https://ak-v.tripcdn.com/videos/1A091t000001i1av39C52.mp4?ts=1622898856678"
		},
		"25":{
			"id": 25,
			"imgs": [
				"https://youimg1.c-ctrip.com/target/10030q000000goy0v1E89_D_750_562_Q90.jpg?proc=autoorient",
				"https://youimg1.c-ctrip.com/target/10090q000000gc0wr3753_D_750_562_Q90.jpg?proc=autoorient",
				"https://youimg1.c-ctrip.com/target/100l0q000000gndqr589A_D_750_562_Q90.jpg?proc=autoorient"
			],
			"name": "天属阁",
			"score": 4.7,
			"reviews": 794,
			"avgPrice": 840,
			"exactPosition": "南京西路250号静安洲际酒店39楼",
			"generalPosition": "淮海路/新天地地区",
			"style": "川菜",
			"duration": [
				[
					11,
					13.5
				],
				[
					17,
					21
				]
			],
			"tel": "16616409764",
			"distance": 6997,
			"video": "https://ak-v.tripcdn.com/videos/1A091t000001i1av39C52.mp4?ts=1622898856678"
		},
		"26":{
			"id": 26,
			"imgs": [
				"https://youimg1.c-ctrip.com/target/10030q000000goy0v1E89_D_750_562_Q90.jpg?proc=autoorient",
				"https://youimg1.c-ctrip.com/target/10090q000000gc0wr3753_D_750_562_Q90.jpg?proc=autoorient",
				"https://youimg1.c-ctrip.com/target/100l0q000000gndqr589A_D_750_562_Q90.jpg?proc=autoorient"
			],
			"name": "梅亭自助寿喜锅",
			"score": 4.2,
			"reviews": 517,
			"avgPrice": 245,
			"exactPosition": "长宁区昭化路512-6号",
			"generalPosition": "淮海路/新天地地区",
			"style": "日式火锅",
			"duration": [
				[
					11,
					13.5
				],
				[
					17,
					21
				]
			],
			"tel": "15183824326",
			"distance": 6817,
			"video": "https://ak-v.tripcdn.com/videos/1A091t000001i1av39C52.mp4?ts=1622898856678"
		},
		"27":{
			"id": 27,
			"imgs": [
				"https://youimg1.c-ctrip.com/target/10030q000000goy0v1E89_D_750_562_Q90.jpg?proc=autoorient",
				"https://youimg1.c-ctrip.com/target/10090q000000gc0wr3753_D_750_562_Q90.jpg?proc=autoorient",
				"https://youimg1.c-ctrip.com/target/100l0q000000gndqr589A_D_750_562_Q90.jpg?proc=autoorient"
			],
			"name": "香满堂",
			"score": 4.5,
			"reviews": 902,
			"avgPrice": 205,
			"exactPosition": "斜土二路111号",
			"generalPosition": "淮海路/新天地地区",
			"style": "小龙虾",
			"duration": [
				[
					11,
					13.5
				],
				[
					17,
					21
				]
			],
			"tel": "15878574107",
			"distance": 2136,
			"video": "https://ak-v.tripcdn.com/videos/1A091t000001i1av39C52.mp4?ts=1622898856678"
		},
		"28":{
			"id": 28,
			"imgs": [
				"https://youimg1.c-ctrip.com/target/10030q000000goy0v1E89_D_750_562_Q90.jpg?proc=autoorient",
				"https://youimg1.c-ctrip.com/target/10090q000000gc0wr3753_D_750_562_Q90.jpg?proc=autoorient",
				"https://youimg1.c-ctrip.com/target/100l0q000000gndqr589A_D_750_562_Q90.jpg?proc=autoorient"
			],
			"name": "滨寿司",
			"score": 4.9,
			"reviews": 77,
			"avgPrice": 834,
			"exactPosition": "长宁区天山路341、345号BINGO缤谷广场F3",
			"generalPosition": "淮海路/新天地地区",
			"style": "寿司",
			"duration": [
				[
					11,
					13.5
				],
				[
					17,
					21
				]
			],
			"tel": "18246239455",
			"distance": 5838,
			"video": "https://ak-v.tripcdn.com/videos/1A091t000001i1av39C52.mp4?ts=1622898856678"
		},
		"29":{
			"id": 29,
			"imgs": [
				"https://youimg1.c-ctrip.com/target/10030q000000goy0v1E89_D_750_562_Q90.jpg?proc=autoorient",
				"https://youimg1.c-ctrip.com/target/10090q000000gc0wr3753_D_750_562_Q90.jpg?proc=autoorient",
				"https://youimg1.c-ctrip.com/target/100l0q000000gndqr589A_D_750_562_Q90.jpg?proc=autoorient"
			],
			"name": "博多新记",
			"score": 4.7,
			"reviews": 245,
			"avgPrice": 278,
			"exactPosition": "徐汇区复兴中路1252弄15号弄堂里",
			"generalPosition": "淮海路/新天地地区",
			"style": "粤菜",
			"duration": [
				[
					11,
					13.5
				],
				[
					17,
					21
				]
			],
			"tel": "13881566618",
			"distance": 3524,
			"video": "https://ak-v.tripcdn.com/videos/1A091t000001i1av39C52.mp4?ts=1622898856678"
		},
		"30":{
			"id": 30,
			"imgs": [
				"https://youimg1.c-ctrip.com/target/10030q000000goy0v1E89_D_750_562_Q90.jpg?proc=autoorient",
				"https://youimg1.c-ctrip.com/target/10090q000000gc0wr3753_D_750_562_Q90.jpg?proc=autoorient",
				"https://youimg1.c-ctrip.com/target/100l0q000000gndqr589A_D_750_562_Q90.jpg?proc=autoorient"
			],
			"name": "眉州东坡酒楼",
			"score": 4.7,
			"reviews": 225,
			"avgPrice": 282,
			"exactPosition": "陆家嘴西路168号正大广场8楼",
			"generalPosition": "淮海路/新天地地区",
			"style": "川菜",
			"duration": [
				[
					11,
					13.5
				],
				[
					17,
					21
				]
			],
			"tel": "14681988501",
			"distance": 8648,
			"video": "https://ak-v.tripcdn.com/videos/1A091t000001i1av39C52.mp4?ts=1622898856678"
		},
		"31":{
			"id": 31,
			"imgs": [
				"https://youimg1.c-ctrip.com/target/10030q000000goy0v1E89_D_750_562_Q90.jpg?proc=autoorient",
				"https://youimg1.c-ctrip.com/target/10090q000000gc0wr3753_D_750_562_Q90.jpg?proc=autoorient",
				"https://youimg1.c-ctrip.com/target/100l0q000000gndqr589A_D_750_562_Q90.jpg?proc=autoorient"
			],
			"name": "Mamma Mia",
			"score": 3.7,
			"reviews": 321,
			"avgPrice": 374,
			"exactPosition": "淮海中路1333号永新坊1楼",
			"generalPosition": "淮海路/新天地地区",
			"style": "披萨",
			"duration": [
				[
					11,
					13.5
				],
				[
					17,
					21
				]
			],
			"tel": "15390409425",
			"distance": 6215,
			"video": "https://ak-v.tripcdn.com/videos/1A091t000001i1av39C52.mp4?ts=1622898856678"
		},
		"32":{
			"id": 32,
			"imgs": [
				"https://youimg1.c-ctrip.com/target/10030q000000goy0v1E89_D_750_562_Q90.jpg?proc=autoorient",
				"https://youimg1.c-ctrip.com/target/10090q000000gc0wr3753_D_750_562_Q90.jpg?proc=autoorient",
				"https://youimg1.c-ctrip.com/target/100l0q000000gndqr589A_D_750_562_Q90.jpg?proc=autoorient"
			],
			"name": "祥和面馆",
			"score": 4.6,
			"reviews": 742,
			"avgPrice": 240,
			"exactPosition": "长宁区定西路1235弄1号",
			"generalPosition": "淮海路/新天地地区",
			"style": "面食",
			"duration": [
				[
					11,
					13.5
				],
				[
					17,
					21
				]
			],
			"tel": "18142924498",
			"distance": 3693,
			"video": "https://ak-v.tripcdn.com/videos/1A091t000001i1av39C52.mp4?ts=1622898856678"
		},
		"33":{
			"id": 33,
			"imgs": [
				"https://youimg1.c-ctrip.com/target/10030q000000goy0v1E89_D_750_562_Q90.jpg?proc=autoorient",
				"https://youimg1.c-ctrip.com/target/10090q000000gc0wr3753_D_750_562_Q90.jpg?proc=autoorient",
				"https://youimg1.c-ctrip.com/target/100l0q000000gndqr589A_D_750_562_Q90.jpg?proc=autoorient"
			],
			"name": "岳阳楼湘菜馆",
			"score": 4.3,
			"reviews": 39,
			"avgPrice": 411,
			"exactPosition": "闵行区沪青平公路165号",
			"generalPosition": "淮海路/新天地地区",
			"style": "湘菜",
			"duration": [
				[
					11,
					13.5
				],
				[
					17,
					21
				]
			],
			"tel": "17127317148",
			"distance": 7258,
			"video": "https://ak-v.tripcdn.com/videos/1A091t000001i1av39C52.mp4?ts=1622898856678"
		},
		"34":{
			"id": 34,
			"imgs": [
				"https://youimg1.c-ctrip.com/target/10030q000000goy0v1E89_D_750_562_Q90.jpg?proc=autoorient",
				"https://youimg1.c-ctrip.com/target/10090q000000gc0wr3753_D_750_562_Q90.jpg?proc=autoorient",
				"https://youimg1.c-ctrip.com/target/100l0q000000gndqr589A_D_750_562_Q90.jpg?proc=autoorient"
			],
			"name": "Epices Foie Gras",
			"score": 4.2,
			"reviews": 607,
			"avgPrice": 462,
			"exactPosition": "黄浦区汉口路309号A1-05号",
			"generalPosition": "淮海路/新天地地区",
			"style": "法国菜",
			"duration": [
				[
					11,
					13.5
				],
				[
					17,
					21
				]
			],
			"tel": "15656742815",
			"distance": 9602,
			"video": "https://ak-v.tripcdn.com/videos/1A091t000001i1av39C52.mp4?ts=1622898856678"
		},
		"35":{
			"id": 35,
			"imgs": [
				"https://youimg1.c-ctrip.com/target/10030q000000goy0v1E89_D_750_562_Q90.jpg?proc=autoorient",
				"https://youimg1.c-ctrip.com/target/10090q000000gc0wr3753_D_750_562_Q90.jpg?proc=autoorient",
				"https://youimg1.c-ctrip.com/target/100l0q000000gndqr589A_D_750_562_Q90.jpg?proc=autoorient"
			],
			"name": "御鲤湘",
			"score": 4.4,
			"reviews": 76,
			"avgPrice": 431,
			"exactPosition": "静安区北京西路1135号",
			"generalPosition": "淮海路/新天地地区",
			"style": "湘菜",
			"duration": [
				[
					11,
					13.5
				],
				[
					17,
					21
				]
			],
			"tel": "18379356168",
			"distance": 9777,
			"video": "https://ak-v.tripcdn.com/videos/1A091t000001i1av39C52.mp4?ts=1622898856678"
		},
		"36":{
			"id": 36,
			"imgs": [
				"https://youimg1.c-ctrip.com/target/10030q000000goy0v1E89_D_750_562_Q90.jpg?proc=autoorient",
				"https://youimg1.c-ctrip.com/target/10090q000000gc0wr3753_D_750_562_Q90.jpg?proc=autoorient",
				"https://youimg1.c-ctrip.com/target/100l0q000000gndqr589A_D_750_562_Q90.jpg?proc=autoorient"
			],
			"name": "飞象西餐厅",
			"score": 4.6,
			"reviews": 457,
			"avgPrice": 779,
			"exactPosition": "静安区共和新路2750号锦荣国际大酒店1楼",
			"generalPosition": "淮海路/新天地地区",
			"style": "俄罗斯菜",
			"duration": [
				[
					11,
					13.5
				],
				[
					17,
					21
				]
			],
			"tel": "14686331356",
			"distance": 2031,
			"video": "https://ak-v.tripcdn.com/videos/1A091t000001i1av39C52.mp4?ts=1622898856678"
		},
		"37":{
			"id": 37,
			"imgs": [
				"https://youimg1.c-ctrip.com/target/10030q000000goy0v1E89_D_750_562_Q90.jpg?proc=autoorient",
				"https://youimg1.c-ctrip.com/target/10090q000000gc0wr3753_D_750_562_Q90.jpg?proc=autoorient",
				"https://youimg1.c-ctrip.com/target/100l0q000000gndqr589A_D_750_562_Q90.jpg?proc=autoorient"
			],
			"name": "牛赞日式自助火锅料理",
			"score": 3.7,
			"reviews": 123,
			"avgPrice": 762,
			"exactPosition": "浦东新区金海路2505号上海曹路宝龙广场F1",
			"generalPosition": "淮海路/新天地地区",
			"style": "日式火锅",
			"duration": [
				[
					11,
					13.5
				],
				[
					17,
					21
				]
			],
			"tel": "17110337848",
			"distance": 9671,
			"video": "https://ak-v.tripcdn.com/videos/1A091t000001i1av39C52.mp4?ts=1622898856678"
		},
		"38":{
			"id": 38,
			"imgs": [
				"https://youimg1.c-ctrip.com/target/10030q000000goy0v1E89_D_750_562_Q90.jpg?proc=autoorient",
				"https://youimg1.c-ctrip.com/target/10090q000000gc0wr3753_D_750_562_Q90.jpg?proc=autoorient",
				"https://youimg1.c-ctrip.com/target/100l0q000000gndqr589A_D_750_562_Q90.jpg?proc=autoorient"
			],
			"name": "一锅入魂和牛自助寿喜烧",
			"score": 3.2,
			"reviews": 179,
			"avgPrice": 282,
			"exactPosition": "黄浦区福建中路355号3层",
			"generalPosition": "淮海路/新天地地区",
			"style": "日式火锅",
			"duration": [
				[
					11,
					13.5
				],
				[
					17,
					21
				]
			],
			"tel": "18953382351",
			"distance": 7795,
			"video": "https://ak-v.tripcdn.com/videos/1A091t000001i1av39C52.mp4?ts=1622898856678"
		},
		"39":{
			"id": 39,
			"imgs": [
				"https://youimg1.c-ctrip.com/target/10030q000000goy0v1E89_D_750_562_Q90.jpg?proc=autoorient",
				"https://youimg1.c-ctrip.com/target/10090q000000gc0wr3753_D_750_562_Q90.jpg?proc=autoorient",
				"https://youimg1.c-ctrip.com/target/100l0q000000gndqr589A_D_750_562_Q90.jpg?proc=autoorient"
			],
			"name": "小杨生煎(黄河路店)",
			"score": 3.3,
			"reviews": 561,
			"avgPrice": 173,
			"exactPosition": "黄浦区黄河路97号",
			"generalPosition": "淮海路/新天地地区",
			"style": "中式快餐",
			"duration": [
				[
					11,
					13.5
				],
				[
					17,
					21
				]
			],
			"tel": "18374628846",
			"distance": 474,
			"video": "https://ak-v.tripcdn.com/videos/1A091t000001i1av39C52.mp4?ts=1622898856678"
		},
		"40":{
			"id": 40,
			"imgs": [
				"https://youimg1.c-ctrip.com/target/10030q000000goy0v1E89_D_750_562_Q90.jpg?proc=autoorient",
				"https://youimg1.c-ctrip.com/target/10090q000000gc0wr3753_D_750_562_Q90.jpg?proc=autoorient",
				"https://youimg1.c-ctrip.com/target/100l0q000000gndqr589A_D_750_562_Q90.jpg?proc=autoorient"
			],
			"name": "CASANOVA意大利餐厅",
			"score": 3.8,
			"reviews": 645,
			"avgPrice": 561,
			"exactPosition": "黄浦区中山东一路6号外滩6号b座4楼",
			"generalPosition": "淮海路/新天地地区",
			"style": "意大利菜",
			"duration": [
				[
					11,
					13.5
				],
				[
					17,
					21
				]
			],
			"tel": "17606864790",
			"distance": 5308,
			"video": "https://ak-v.tripcdn.com/videos/1A091t000001i1av39C52.mp4?ts=1622898856678"
		},
		"41":{
			"id": 41,
			"imgs": [
				"https://youimg1.c-ctrip.com/target/10030q000000goy0v1E89_D_750_562_Q90.jpg?proc=autoorient",
				"https://youimg1.c-ctrip.com/target/10090q000000gc0wr3753_D_750_562_Q90.jpg?proc=autoorient",
				"https://youimg1.c-ctrip.com/target/100l0q000000gndqr589A_D_750_562_Q90.jpg?proc=autoorient"
			],
			"name": "美粤华·精致粤菜",
			"score": 4.7,
			"reviews": 637,
			"avgPrice": 463,
			"exactPosition": "徐汇区肇嘉浜路238号5楼陕西南路口",
			"generalPosition": "淮海路/新天地地区",
			"style": "粤菜",
			"duration": [
				[
					11,
					13.5
				],
				[
					17,
					21
				]
			],
			"tel": "19875856560",
			"distance": 5859,
			"video": "https://ak-v.tripcdn.com/videos/1A091t000001i1av39C52.mp4?ts=1622898856678"
		},
		"42":{
			"id": 42,
			"imgs": [
				"https://youimg1.c-ctrip.com/target/10030q000000goy0v1E89_D_750_562_Q90.jpg?proc=autoorient",
				"https://youimg1.c-ctrip.com/target/10090q000000gc0wr3753_D_750_562_Q90.jpg?proc=autoorient",
				"https://youimg1.c-ctrip.com/target/100l0q000000gndqr589A_D_750_562_Q90.jpg?proc=autoorient"
			],
			"name": "许爷剁椒鱼头",
			"score": 4.7,
			"reviews": 561,
			"avgPrice": 715,
			"exactPosition": "徐汇区宛平南路368号",
			"generalPosition": "淮海路/新天地地区",
			"style": "湘菜",
			"duration": [
				[
					11,
					13.5
				],
				[
					17,
					21
				]
			],
			"tel": "19256475479",
			"distance": 4546,
			"video": "https://ak-v.tripcdn.com/videos/1A091t000001i1av39C52.mp4?ts=1622898856678"
		},
		"43":{
			"id": 43,
			"imgs": [
				"https://youimg1.c-ctrip.com/target/10030q000000goy0v1E89_D_750_562_Q90.jpg?proc=autoorient",
				"https://youimg1.c-ctrip.com/target/10090q000000gc0wr3753_D_750_562_Q90.jpg?proc=autoorient",
				"https://youimg1.c-ctrip.com/target/100l0q000000gndqr589A_D_750_562_Q90.jpg?proc=autoorient"
			],
			"name": "知味面馆",
			"score": 3.7,
			"reviews": 119,
			"avgPrice": 341,
			"exactPosition": "四川中路香港路路口",
			"generalPosition": "淮海路/新天地地区",
			"style": "面食",
			"duration": [
				[
					11,
					13.5
				],
				[
					17,
					21
				]
			],
			"tel": "17841328460",
			"distance": 306,
			"video": "https://ak-v.tripcdn.com/videos/1A091t000001i1av39C52.mp4?ts=1622898856678"
		},
		"44":{
			"id": 44,
			"imgs": [
				"https://youimg1.c-ctrip.com/target/10030q000000goy0v1E89_D_750_562_Q90.jpg?proc=autoorient",
				"https://youimg1.c-ctrip.com/target/10090q000000gc0wr3753_D_750_562_Q90.jpg?proc=autoorient",
				"https://youimg1.c-ctrip.com/target/100l0q000000gndqr589A_D_750_562_Q90.jpg?proc=autoorient"
			],
			"name": "德荣老北京铜锅",
			"score": 4.7,
			"reviews": 61,
			"avgPrice": 771,
			"exactPosition": "杨浦区国和路971号",
			"generalPosition": "淮海路/新天地地区",
			"style": "老北京火锅",
			"duration": [
				[
					11,
					13.5
				],
				[
					17,
					21
				]
			],
			"tel": "16637081237",
			"distance": 374,
			"video": "https://ak-v.tripcdn.com/videos/1A091t000001i1av39C52.mp4?ts=1622898856678"
		},
		"45":{
			"id": 45,
			"imgs": [
				"https://youimg1.c-ctrip.com/target/10030q000000goy0v1E89_D_750_562_Q90.jpg?proc=autoorient",
				"https://youimg1.c-ctrip.com/target/10090q000000gc0wr3753_D_750_562_Q90.jpg?proc=autoorient",
				"https://youimg1.c-ctrip.com/target/100l0q000000gndqr589A_D_750_562_Q90.jpg?proc=autoorient"
			],
			"name": "粤珍轩",
			"score": 4.5,
			"reviews": 50,
			"avgPrice": 380,
			"exactPosition": "闵行区吴中路1155号亚世都酒店2楼(近万源路)",
			"generalPosition": "淮海路/新天地地区",
			"style": "粤菜",
			"duration": [
				[
					11,
					13.5
				],
				[
					17,
					21
				]
			],
			"tel": "16511110816",
			"distance": 9324,
			"video": "https://ak-v.tripcdn.com/videos/1A091t000001i1av39C52.mp4?ts=1622898856678"
		},
		"46":{
			"id": 46,
			"imgs": [
				"https://youimg1.c-ctrip.com/target/10030q000000goy0v1E89_D_750_562_Q90.jpg?proc=autoorient",
				"https://youimg1.c-ctrip.com/target/10090q000000gc0wr3753_D_750_562_Q90.jpg?proc=autoorient",
				"https://youimg1.c-ctrip.com/target/100l0q000000gndqr589A_D_750_562_Q90.jpg?proc=autoorient"
			],
			"name": "聚城老北京爆肚涮肉坊",
			"score": 3.2,
			"reviews": 309,
			"avgPrice": 301,
			"exactPosition": "浦东新区梅花路1099号博览汇广场F1",
			"generalPosition": "淮海路/新天地地区",
			"style": "老北京火锅",
			"duration": [
				[
					11,
					13.5
				],
				[
					17,
					21
				]
			],
			"tel": "14346422826",
			"distance": 6187,
			"video": "https://ak-v.tripcdn.com/videos/1A091t000001i1av39C52.mp4?ts=1622898856678"
		},
		"47":{
			"id": 47,
			"imgs": [
				"https://youimg1.c-ctrip.com/target/10030q000000goy0v1E89_D_750_562_Q90.jpg?proc=autoorient",
				"https://youimg1.c-ctrip.com/target/10090q000000gc0wr3753_D_750_562_Q90.jpg?proc=autoorient",
				"https://youimg1.c-ctrip.com/target/100l0q000000gndqr589A_D_750_562_Q90.jpg?proc=autoorient"
			],
			"name": "云中鱼蒸汽石锅鱼",
			"score": 4.4,
			"reviews": 893,
			"avgPrice": 858,
			"exactPosition": "汶水路协信星光广场",
			"generalPosition": "淮海路/新天地地区",
			"style": "鱼火锅",
			"duration": [
				[
					11,
					13.5
				],
				[
					17,
					21
				]
			],
			"tel": "18633742771",
			"distance": 5298,
			"video": "https://ak-v.tripcdn.com/videos/1A091t000001i1av39C52.mp4?ts=1622898856678"
		},
		"48":{
			"id": 48,
			"imgs": [
				"https://youimg1.c-ctrip.com/target/10030q000000goy0v1E89_D_750_562_Q90.jpg?proc=autoorient",
				"https://youimg1.c-ctrip.com/target/10090q000000gc0wr3753_D_750_562_Q90.jpg?proc=autoorient",
				"https://youimg1.c-ctrip.com/target/100l0q000000gndqr589A_D_750_562_Q90.jpg?proc=autoorient"
			],
			"name": "老北京涮羊肉纪翟路",
			"score": 4.1,
			"reviews": 845,
			"avgPrice": 313,
			"exactPosition": "纪翟路250号1层",
			"generalPosition": "淮海路/新天地地区",
			"style": "老北京火锅",
			"duration": [
				[
					11,
					13.5
				],
				[
					17,
					21
				]
			],
			"tel": "14289666121",
			"distance": 1205,
			"video": "https://ak-v.tripcdn.com/videos/1A091t000001i1av39C52.mp4?ts=1622898856678"
		},
		"49":{
			"id": 49,
			"imgs": [
				"https://youimg1.c-ctrip.com/target/10030q000000goy0v1E89_D_750_562_Q90.jpg?proc=autoorient",
				"https://youimg1.c-ctrip.com/target/10090q000000gc0wr3753_D_750_562_Q90.jpg?proc=autoorient",
				"https://youimg1.c-ctrip.com/target/100l0q000000gndqr589A_D_750_562_Q90.jpg?proc=autoorient"
			],
			"name": "达美乐披萨",
			"score": 4.6,
			"reviews": 475,
			"avgPrice": 955,
			"exactPosition": "平阳路1481-2临",
			"generalPosition": "淮海路/新天地地区",
			"style": "披萨",
			"duration": [
				[
					11,
					13.5
				],
				[
					17,
					21
				]
			],
			"tel": "19441302067",
			"distance": 4288,
			"video": "https://ak-v.tripcdn.com/videos/1A091t000001i1av39C52.mp4?ts=1622898856678"
		},
		"50":{
			"id": 50,
			"imgs": [
				"https://youimg1.c-ctrip.com/target/10030q000000goy0v1E89_D_750_562_Q90.jpg?proc=autoorient",
				"https://youimg1.c-ctrip.com/target/10090q000000gc0wr3753_D_750_562_Q90.jpg?proc=autoorient",
				"https://youimg1.c-ctrip.com/target/100l0q000000gndqr589A_D_750_562_Q90.jpg?proc=autoorient"
			],
			"name": "PASTA WANG",
			"score": 4.8,
			"reviews": 811,
			"avgPrice": 363,
			"exactPosition": "长宁区仙霞路99号虹桥古北商务区B座1楼",
			"generalPosition": "淮海路/新天地地区",
			"style": "西式快餐",
			"duration": [
				[
					11,
					13.5
				],
				[
					17,
					21
				]
			],
			"tel": "15218311026",
			"distance": 1335,
			"video": "https://ak-v.tripcdn.com/videos/1A091t000001i1av39C52.mp4?ts=1622898856678"
		},
		"51":{
			"id": 51,
			"imgs": [
				"https://youimg1.c-ctrip.com/target/10030q000000goy0v1E89_D_750_562_Q90.jpg?proc=autoorient",
				"https://youimg1.c-ctrip.com/target/10090q000000gc0wr3753_D_750_562_Q90.jpg?proc=autoorient",
				"https://youimg1.c-ctrip.com/target/100l0q000000gndqr589A_D_750_562_Q90.jpg?proc=autoorient"
			],
			"name": "肯德基",
			"score": 3.3,
			"reviews": 993,
			"avgPrice": 334,
			"exactPosition": "上海市杨浦区双辽路768号",
			"generalPosition": "淮海路/新天地地区",
			"style": "西式快餐",
			"duration": [
				[
					11,
					13.5
				],
				[
					17,
					21
				]
			],
			"tel": "14447064194",
			"distance": 6661,
			"video": "https://ak-v.tripcdn.com/videos/1A091t000001i1av39C52.mp4?ts=1622898856678"
		},
		"52":{
			"id": 52,
			"imgs": [
				"https://youimg1.c-ctrip.com/target/10030q000000goy0v1E89_D_750_562_Q90.jpg?proc=autoorient",
				"https://youimg1.c-ctrip.com/target/10090q000000gc0wr3753_D_750_562_Q90.jpg?proc=autoorient",
				"https://youimg1.c-ctrip.com/target/100l0q000000gndqr589A_D_750_562_Q90.jpg?proc=autoorient"
			],
			"name": "棒约翰披萨",
			"score": 3.9,
			"reviews": 761,
			"avgPrice": 995,
			"exactPosition": "龙阳路2345号新国际博览中心E4馆",
			"generalPosition": "淮海路/新天地地区",
			"style": "披萨",
			"duration": [
				[
					11,
					13.5
				],
				[
					17,
					21
				]
			],
			"tel": "15843885188",
			"distance": 3116,
			"video": "https://ak-v.tripcdn.com/videos/1A091t000001i1av39C52.mp4?ts=1622898856678"
		},
		"53":{
			"id": 53,
			"imgs": [
				"https://youimg1.c-ctrip.com/target/10030q000000goy0v1E89_D_750_562_Q90.jpg?proc=autoorient",
				"https://youimg1.c-ctrip.com/target/10090q000000gc0wr3753_D_750_562_Q90.jpg?proc=autoorient",
				"https://youimg1.c-ctrip.com/target/100l0q000000gndqr589A_D_750_562_Q90.jpg?proc=autoorient"
			],
			"name": "白桦林俄罗斯餐厅",
			"score": 4.8,
			"reviews": 834,
			"avgPrice": 842,
			"exactPosition": "静安区南京西路1376号恒隆广场7楼",
			"generalPosition": "淮海路/新天地地区",
			"style": "俄罗斯菜",
			"duration": [
				[
					11,
					13.5
				],
				[
					17,
					21
				]
			],
			"tel": "15449504560",
			"distance": 9956,
			"video": "https://ak-v.tripcdn.com/videos/1A091t000001i1av39C52.mp4?ts=1622898856678"
		},
		"54":{
			"id": 54,
			"imgs": [
				"https://youimg1.c-ctrip.com/target/10030q000000goy0v1E89_D_750_562_Q90.jpg?proc=autoorient",
				"https://youimg1.c-ctrip.com/target/10090q000000gc0wr3753_D_750_562_Q90.jpg?proc=autoorient",
				"https://youimg1.c-ctrip.com/target/100l0q000000gndqr589A_D_750_562_Q90.jpg?proc=autoorient"
			],
			"name": "哈尼石锅鱼火锅",
			"score": 3.7,
			"reviews": 147,
			"avgPrice": 270,
			"exactPosition": "世博大道1368号",
			"generalPosition": "淮海路/新天地地区",
			"style": "鱼火锅",
			"duration": [
				[
					11,
					13.5
				],
				[
					17,
					21
				]
			],
			"tel": "15365867763",
			"distance": 4413,
			"video": "https://ak-v.tripcdn.com/videos/1A091t000001i1av39C52.mp4?ts=1622898856678"
		},
		"55":{
			"id": 55,
			"imgs": [
				"https://youimg1.c-ctrip.com/target/10030q000000goy0v1E89_D_750_562_Q90.jpg?proc=autoorient",
				"https://youimg1.c-ctrip.com/target/10090q000000gc0wr3753_D_750_562_Q90.jpg?proc=autoorient",
				"https://youimg1.c-ctrip.com/target/100l0q000000gndqr589A_D_750_562_Q90.jpg?proc=autoorient"
			],
			"name": "诚家",
			"score": 4.6,
			"reviews": 466,
			"avgPrice": 850,
			"exactPosition": "长宁区安龙路100号1楼",
			"generalPosition": "淮海路/新天地地区",
			"style": "居酒屋",
			"duration": [
				[
					11,
					13.5
				],
				[
					17,
					21
				]
			],
			"tel": "18675839422",
			"distance": 3191,
			"video": "https://ak-v.tripcdn.com/videos/1A091t000001i1av39C52.mp4?ts=1622898856678"
		},
		"56":{
			"id": 56,
			"imgs": [
				"https://youimg1.c-ctrip.com/target/10030q000000goy0v1E89_D_750_562_Q90.jpg?proc=autoorient",
				"https://youimg1.c-ctrip.com/target/10090q000000gc0wr3753_D_750_562_Q90.jpg?proc=autoorient",
				"https://youimg1.c-ctrip.com/target/100l0q000000gndqr589A_D_750_562_Q90.jpg?proc=autoorient"
			],
			"name": "严记老北京涮锅",
			"score": 3.1,
			"reviews": 557,
			"avgPrice": 689,
			"exactPosition": "徐汇区乌鲁木齐中路346号1楼(近复兴西路)",
			"generalPosition": "淮海路/新天地地区",
			"style": "老北京火锅",
			"duration": [
				[
					11,
					13.5
				],
				[
					17,
					21
				]
			],
			"tel": "16243543572",
			"distance": 159,
			"video": "https://ak-v.tripcdn.com/videos/1A091t000001i1av39C52.mp4?ts=1622898856678"
		},
		"57":{
			"id": 57,
			"imgs": [
				"https://youimg1.c-ctrip.com/target/10030q000000goy0v1E89_D_750_562_Q90.jpg?proc=autoorient",
				"https://youimg1.c-ctrip.com/target/10090q000000gc0wr3753_D_750_562_Q90.jpg?proc=autoorient",
				"https://youimg1.c-ctrip.com/target/100l0q000000gndqr589A_D_750_562_Q90.jpg?proc=autoorient"
			],
			"name": "依水园寿司屋",
			"score": 4.1,
			"reviews": 377,
			"avgPrice": 743,
			"exactPosition": "浦东新区林展路380号",
			"generalPosition": "淮海路/新天地地区",
			"style": "寿司",
			"duration": [
				[
					11,
					13.5
				],
				[
					17,
					21
				]
			],
			"tel": "18612122734",
			"distance": 714,
			"video": "https://ak-v.tripcdn.com/videos/1A091t000001i1av39C52.mp4?ts=1622898856678"
		},
		"58":{
			"id": 58,
			"imgs": [
				"https://youimg1.c-ctrip.com/target/10030q000000goy0v1E89_D_750_562_Q90.jpg?proc=autoorient",
				"https://youimg1.c-ctrip.com/target/10090q000000gc0wr3753_D_750_562_Q90.jpg?proc=autoorient",
				"https://youimg1.c-ctrip.com/target/100l0q000000gndqr589A_D_750_562_Q90.jpg?proc=autoorient"
			],
			"name": "大龙燚",
			"score": 4.9,
			"reviews": 345,
			"avgPrice": 215,
			"exactPosition": "淮海中路999号百盛购物中心7楼",
			"generalPosition": "淮海路/新天地地区",
			"style": "重庆火锅",
			"duration": [
				[
					11,
					13.5
				],
				[
					17,
					21
				]
			],
			"tel": "16711674815",
			"distance": 1420,
			"video": "https://ak-v.tripcdn.com/videos/1A091t000001i1av39C52.mp4?ts=1622898856678"
		},
		"59":{
			"id": 59,
			"imgs": [
				"https://youimg1.c-ctrip.com/target/10030q000000goy0v1E89_D_750_562_Q90.jpg?proc=autoorient",
				"https://youimg1.c-ctrip.com/target/10090q000000gc0wr3753_D_750_562_Q90.jpg?proc=autoorient",
				"https://youimg1.c-ctrip.com/target/100l0q000000gndqr589A_D_750_562_Q90.jpg?proc=autoorient"
			],
			"name": "老北京涮锅",
			"score": 4.3,
			"reviews": 531,
			"avgPrice": 767,
			"exactPosition": "普陀区宜川路17号",
			"generalPosition": "淮海路/新天地地区",
			"style": "老北京火锅",
			"duration": [
				[
					11,
					13.5
				],
				[
					17,
					21
				]
			],
			"tel": "18331319131",
			"distance": 2156,
			"video": "https://ak-v.tripcdn.com/videos/1A091t000001i1av39C52.mp4?ts=1622898856678"
		},
		"60":{
			"id": 60,
			"imgs": [
				"https://youimg1.c-ctrip.com/target/10030q000000goy0v1E89_D_750_562_Q90.jpg?proc=autoorient",
				"https://youimg1.c-ctrip.com/target/10090q000000gc0wr3753_D_750_562_Q90.jpg?proc=autoorient",
				"https://youimg1.c-ctrip.com/target/100l0q000000gndqr589A_D_750_562_Q90.jpg?proc=autoorient"
			],
			"name": "谭姐湘菜馆",
			"score": 4.8,
			"reviews": 668,
			"avgPrice": 453,
			"exactPosition": "浦东新区浦东大道1028号",
			"generalPosition": "淮海路/新天地地区",
			"style": "湘菜",
			"duration": [
				[
					11,
					13.5
				],
				[
					17,
					21
				]
			],
			"tel": "18421726126",
			"distance": 5173,
			"video": "https://ak-v.tripcdn.com/videos/1A091t000001i1av39C52.mp4?ts=1622898856678"
		},
		"61":{
			"id": 61,
			"imgs": [
				"https://youimg1.c-ctrip.com/target/10030q000000goy0v1E89_D_750_562_Q90.jpg?proc=autoorient",
				"https://youimg1.c-ctrip.com/target/10090q000000gc0wr3753_D_750_562_Q90.jpg?proc=autoorient",
				"https://youimg1.c-ctrip.com/target/100l0q000000gndqr589A_D_750_562_Q90.jpg?proc=autoorient"
			],
			"name": "卡拉奇俄罗斯餐厅",
			"score": 4.5,
			"reviews": 372,
			"avgPrice": 251,
			"exactPosition": "黄浦区西藏南路268号新世界城市广场5楼",
			"generalPosition": "淮海路/新天地地区",
			"style": "俄罗斯菜",
			"duration": [
				[
					11,
					13.5
				],
				[
					17,
					21
				]
			],
			"tel": "17067271796",
			"distance": 2811,
			"video": "https://ak-v.tripcdn.com/videos/1A091t000001i1av39C52.mp4?ts=1622898856678"
		},
		"62":{
			"id": 62,
			"imgs": [
				"https://youimg1.c-ctrip.com/target/10030q000000goy0v1E89_D_750_562_Q90.jpg?proc=autoorient",
				"https://youimg1.c-ctrip.com/target/10090q000000gc0wr3753_D_750_562_Q90.jpg?proc=autoorient",
				"https://youimg1.c-ctrip.com/target/100l0q000000gndqr589A_D_750_562_Q90.jpg?proc=autoorient"
			],
			"name": "玲姐·海鲜火锅",
			"score": 3.4,
			"reviews": 737,
			"avgPrice": 462,
			"exactPosition": "复兴中路537号思南公馆31栋",
			"generalPosition": "淮海路/新天地地区",
			"style": "鱼火锅",
			"duration": [
				[
					11,
					13.5
				],
				[
					17,
					21
				]
			],
			"tel": "17848927955",
			"distance": 710,
			"video": "https://ak-v.tripcdn.com/videos/1A091t000001i1av39C52.mp4?ts=1622898856678"
		},
		"63":{
			"id": 63,
			"imgs": [
				"https://youimg1.c-ctrip.com/target/10030q000000goy0v1E89_D_750_562_Q90.jpg?proc=autoorient",
				"https://youimg1.c-ctrip.com/target/10090q000000gc0wr3753_D_750_562_Q90.jpg?proc=autoorient",
				"https://youimg1.c-ctrip.com/target/100l0q000000gndqr589A_D_750_562_Q90.jpg?proc=autoorient"
			],
			"name": "张亮麻辣烫",
			"score": 4.3,
			"reviews": 307,
			"avgPrice": 524,
			"exactPosition": "黄浦区天津路128号",
			"generalPosition": "淮海路/新天地地区",
			"style": "麻辣烫",
			"duration": [
				[
					11,
					13.5
				],
				[
					17,
					21
				]
			],
			"tel": "15395257245",
			"distance": 2661,
			"video": "https://ak-v.tripcdn.com/videos/1A091t000001i1av39C52.mp4?ts=1622898856678"
		},
		"64":{
			"id": 64,
			"imgs": [
				"https://youimg1.c-ctrip.com/target/10030q000000goy0v1E89_D_750_562_Q90.jpg?proc=autoorient",
				"https://youimg1.c-ctrip.com/target/10090q000000gc0wr3753_D_750_562_Q90.jpg?proc=autoorient",
				"https://youimg1.c-ctrip.com/target/100l0q000000gndqr589A_D_750_562_Q90.jpg?proc=autoorient"
			],
			"name": "万火酒场",
			"score": 3.7,
			"reviews": 9,
			"avgPrice": 330,
			"exactPosition": "长宁区水城南路333号云古酒店1楼",
			"generalPosition": "淮海路/新天地地区",
			"style": "居酒屋",
			"duration": [
				[
					11,
					13.5
				],
				[
					17,
					21
				]
			],
			"tel": "14583730237",
			"distance": 1998,
			"video": "https://ak-v.tripcdn.com/videos/1A091t000001i1av39C52.mp4?ts=1622898856678"
		},
		"65":{
			"id": 65,
			"imgs": [
				"https://youimg1.c-ctrip.com/target/10030q000000goy0v1E89_D_750_562_Q90.jpg?proc=autoorient",
				"https://youimg1.c-ctrip.com/target/10090q000000gc0wr3753_D_750_562_Q90.jpg?proc=autoorient",
				"https://youimg1.c-ctrip.com/target/100l0q000000gndqr589A_D_750_562_Q90.jpg?proc=autoorient"
			],
			"name": "小杨生煎(虹桥火车站店)",
			"score": 4.9,
			"reviews": 384,
			"avgPrice": 374,
			"exactPosition": "上海市闵行区虹桥路2550号虹桥阿里中心t2楼b1层",
			"generalPosition": "淮海路/新天地地区",
			"style": "中式快餐",
			"duration": [
				[
					11,
					13.5
				],
				[
					17,
					21
				]
			],
			"tel": "19250616466",
			"distance": 2816,
			"video": "https://ak-v.tripcdn.com/videos/1A091t000001i1av39C52.mp4?ts=1622898856678"
		},
		"66":{
			"id": 66,
			"imgs": [
				"https://youimg1.c-ctrip.com/target/10030q000000goy0v1E89_D_750_562_Q90.jpg?proc=autoorient",
				"https://youimg1.c-ctrip.com/target/10090q000000gc0wr3753_D_750_562_Q90.jpg?proc=autoorient",
				"https://youimg1.c-ctrip.com/target/100l0q000000gndqr589A_D_750_562_Q90.jpg?proc=autoorient"
			],
			"name": "甬府(黄浦店)",
			"score": 4.7,
			"reviews": 813,
			"avgPrice": 212,
			"exactPosition": "茂名南路59号锦江饭店锦北楼12层(近长乐路)距地铁1号线陕西南路站(3口)467m，步行6min",
			"generalPosition": "淮海路/新天地地区",
			"style": "江浙菜",
			"duration": [
				[
					11,
					13.5
				],
				[
					17,
					21
				]
			],
			"tel": "18656274525",
			"distance": 2731,
			"video": "https://ak-v.tripcdn.com/videos/1A091t000001i1av39C52.mp4?ts=1622898856678"
		},
		"67":{
			"id": 67,
			"imgs": [
				"https://youimg1.c-ctrip.com/target/10030q000000goy0v1E89_D_750_562_Q90.jpg?proc=autoorient",
				"https://youimg1.c-ctrip.com/target/10090q000000gc0wr3753_D_750_562_Q90.jpg?proc=autoorient",
				"https://youimg1.c-ctrip.com/target/100l0q000000gndqr589A_D_750_562_Q90.jpg?proc=autoorient"
			],
			"name": "小杨生煎(118广场店)",
			"score": 3.3,
			"reviews": 12,
			"avgPrice": 761,
			"exactPosition": "上海市普陀区金沙江路1685号118广场B1",
			"generalPosition": "淮海路/新天地地区",
			"style": "中式快餐",
			"duration": [
				[
					11,
					13.5
				],
				[
					17,
					21
				]
			],
			"tel": "13325831208",
			"distance": 8957,
			"video": "https://ak-v.tripcdn.com/videos/1A091t000001i1av39C52.mp4?ts=1622898856678"
		},
		"68":{
			"id": 68,
			"imgs": [
				"https://youimg1.c-ctrip.com/target/10030q000000goy0v1E89_D_750_562_Q90.jpg?proc=autoorient",
				"https://youimg1.c-ctrip.com/target/10090q000000gc0wr3753_D_750_562_Q90.jpg?proc=autoorient",
				"https://youimg1.c-ctrip.com/target/100l0q000000gndqr589A_D_750_562_Q90.jpg?proc=autoorient"
			],
			"name": "元气寿司",
			"score": 4.7,
			"reviews": 685,
			"avgPrice": 752,
			"exactPosition": "普陀区中山北路3300号Global HarborB2",
			"generalPosition": "淮海路/新天地地区",
			"style": "寿司",
			"duration": [
				[
					11,
					13.5
				],
				[
					17,
					21
				]
			],
			"tel": "16884425848",
			"distance": 4803,
			"video": "https://ak-v.tripcdn.com/videos/1A091t000001i1av39C52.mp4?ts=1622898856678"
		},
		"69":{
			"id": 69,
			"imgs": [
				"https://youimg1.c-ctrip.com/target/10030q000000goy0v1E89_D_750_562_Q90.jpg?proc=autoorient",
				"https://youimg1.c-ctrip.com/target/10090q000000gc0wr3753_D_750_562_Q90.jpg?proc=autoorient",
				"https://youimg1.c-ctrip.com/target/100l0q000000gndqr589A_D_750_562_Q90.jpg?proc=autoorient"
			],
			"name": "伊洛斋日式海鲜火锅",
			"score": 4.1,
			"reviews": 505,
			"avgPrice": 773,
			"exactPosition": "浦东新区松林路357号-1楼",
			"generalPosition": "淮海路/新天地地区",
			"style": "日式火锅",
			"duration": [
				[
					11,
					13.5
				],
				[
					17,
					21
				]
			],
			"tel": "15296555251",
			"distance": 1865,
			"video": "https://ak-v.tripcdn.com/videos/1A091t000001i1av39C52.mp4?ts=1622898856678"
		},
		"70":{
			"id": 70,
			"imgs": [
				"https://youimg1.c-ctrip.com/target/10030q000000goy0v1E89_D_750_562_Q90.jpg?proc=autoorient",
				"https://youimg1.c-ctrip.com/target/10090q000000gc0wr3753_D_750_562_Q90.jpg?proc=autoorient",
				"https://youimg1.c-ctrip.com/target/100l0q000000gndqr589A_D_750_562_Q90.jpg?proc=autoorient"
			],
			"name": "孔乙己尚宴",
			"score": 3.2,
			"reviews": 450,
			"avgPrice": 636,
			"exactPosition": "滨江大道88号贝轩大公馆",
			"generalPosition": "淮海路/新天地地区",
			"style": "江浙菜",
			"duration": [
				[
					11,
					13.5
				],
				[
					17,
					21
				]
			],
			"tel": "15426801217",
			"distance": 161,
			"video": "https://ak-v.tripcdn.com/videos/1A091t000001i1av39C52.mp4?ts=1622898856678"
		},
		"71":{
			"id": 71,
			"imgs": [
				"https://youimg1.c-ctrip.com/target/10030q000000goy0v1E89_D_750_562_Q90.jpg?proc=autoorient",
				"https://youimg1.c-ctrip.com/target/10090q000000gc0wr3753_D_750_562_Q90.jpg?proc=autoorient",
				"https://youimg1.c-ctrip.com/target/100l0q000000gndqr589A_D_750_562_Q90.jpg?proc=autoorient"
			],
			"name": "辣堂·现炒江西米粉",
			"score": 3.5,
			"reviews": 971,
			"avgPrice": 690,
			"exactPosition": "黄浦区宁波路214号E座",
			"generalPosition": "淮海路/新天地地区",
			"style": "米粉/米线",
			"duration": [
				[
					11,
					13.5
				],
				[
					17,
					21
				]
			],
			"tel": "14681487614",
			"distance": 4340,
			"video": "https://ak-v.tripcdn.com/videos/1A091t000001i1av39C52.mp4?ts=1622898856678"
		},
		"72":{
			"id": 72,
			"imgs": [
				"https://youimg1.c-ctrip.com/target/10030q000000goy0v1E89_D_750_562_Q90.jpg?proc=autoorient",
				"https://youimg1.c-ctrip.com/target/10090q000000gc0wr3753_D_750_562_Q90.jpg?proc=autoorient",
				"https://youimg1.c-ctrip.com/target/100l0q000000gndqr589A_D_750_562_Q90.jpg?proc=autoorient"
			],
			"name": "辣府",
			"score": 4.3,
			"reviews": 633,
			"avgPrice": 375,
			"exactPosition": "淮海中路918号香港广场南座5楼",
			"generalPosition": "淮海路/新天地地区",
			"style": "重庆火锅",
			"duration": [
				[
					11,
					13.5
				],
				[
					17,
					21
				]
			],
			"tel": "17048702564",
			"distance": 7988,
			"video": "https://ak-v.tripcdn.com/videos/1A091t000001i1av39C52.mp4?ts=1622898856678"
		},
		"73":{
			"id": 73,
			"imgs": [
				"https://youimg1.c-ctrip.com/target/10030q000000goy0v1E89_D_750_562_Q90.jpg?proc=autoorient",
				"https://youimg1.c-ctrip.com/target/10090q000000gc0wr3753_D_750_562_Q90.jpg?proc=autoorient",
				"https://youimg1.c-ctrip.com/target/100l0q000000gndqr589A_D_750_562_Q90.jpg?proc=autoorient"
			],
			"name": "老爸披萨",
			"score": 3.3,
			"reviews": 431,
			"avgPrice": 615,
			"exactPosition": "水城路576号",
			"generalPosition": "淮海路/新天地地区",
			"style": "披萨",
			"duration": [
				[
					11,
					13.5
				],
				[
					17,
					21
				]
			],
			"tel": "13776129686",
			"distance": 6317,
			"video": "https://ak-v.tripcdn.com/videos/1A091t000001i1av39C52.mp4?ts=1622898856678"
		},
		"74":{
			"id": 74,
			"imgs": [
				"https://youimg1.c-ctrip.com/target/10030q000000goy0v1E89_D_750_562_Q90.jpg?proc=autoorient",
				"https://youimg1.c-ctrip.com/target/10090q000000gc0wr3753_D_750_562_Q90.jpg?proc=autoorient",
				"https://youimg1.c-ctrip.com/target/100l0q000000gndqr589A_D_750_562_Q90.jpg?proc=autoorient"
			],
			"name": "大蒜土耳其餐厅",
			"score": 4.6,
			"reviews": 817,
			"avgPrice": 858,
			"exactPosition": "永嘉路698号",
			"generalPosition": "淮海路/新天地地区",
			"style": "俄罗斯菜",
			"duration": [
				[
					11,
					13.5
				],
				[
					17,
					21
				]
			],
			"tel": "16651795369",
			"distance": 6389,
			"video": "https://ak-v.tripcdn.com/videos/1A091t000001i1av39C52.mp4?ts=1622898856678"
		},
		"75":{
			"id": 75,
			"imgs": [
				"https://youimg1.c-ctrip.com/target/10030q000000goy0v1E89_D_750_562_Q90.jpg?proc=autoorient",
				"https://youimg1.c-ctrip.com/target/10090q000000gc0wr3753_D_750_562_Q90.jpg?proc=autoorient",
				"https://youimg1.c-ctrip.com/target/100l0q000000gndqr589A_D_750_562_Q90.jpg?proc=autoorient"
			],
			"name": "红场俄罗斯西餐厅",
			"score": 3.3,
			"reviews": 713,
			"avgPrice": 798,
			"exactPosition": "虹口区沙泾路10号1933老场坊1号楼308室近九龙宾馆",
			"generalPosition": "淮海路/新天地地区",
			"style": "俄罗斯菜",
			"duration": [
				[
					11,
					13.5
				],
				[
					17,
					21
				]
			],
			"tel": "17397668128",
			"distance": 7698,
			"video": "https://ak-v.tripcdn.com/videos/1A091t000001i1av39C52.mp4?ts=1622898856678"
		},
		"76":{
			"id": 76,
			"imgs": [
				"https://youimg1.c-ctrip.com/target/10030q000000goy0v1E89_D_750_562_Q90.jpg?proc=autoorient",
				"https://youimg1.c-ctrip.com/target/10090q000000gc0wr3753_D_750_562_Q90.jpg?proc=autoorient",
				"https://youimg1.c-ctrip.com/target/100l0q000000gndqr589A_D_750_562_Q90.jpg?proc=autoorient"
			],
			"name": "见龙卸甲",
			"score": 4.3,
			"reviews": 523,
			"avgPrice": 502,
			"exactPosition": "漕宝路1000号",
			"generalPosition": "淮海路/新天地地区",
			"style": "小龙虾",
			"duration": [
				[
					11,
					13.5
				],
				[
					17,
					21
				]
			],
			"tel": "15493282532",
			"distance": 1854,
			"video": "https://ak-v.tripcdn.com/videos/1A091t000001i1av39C52.mp4?ts=1622898856678"
		},
		"77":{
			"id": 77,
			"imgs": [
				"https://youimg1.c-ctrip.com/target/10030q000000goy0v1E89_D_750_562_Q90.jpg?proc=autoorient",
				"https://youimg1.c-ctrip.com/target/10090q000000gc0wr3753_D_750_562_Q90.jpg?proc=autoorient",
				"https://youimg1.c-ctrip.com/target/100l0q000000gndqr589A_D_750_562_Q90.jpg?proc=autoorient"
			],
			"name": "天鹅申阁西菜社",
			"score": 4.3,
			"reviews": 548,
			"avgPrice": 176,
			"exactPosition": "黄浦区进贤路169号",
			"generalPosition": "淮海路/新天地地区",
			"style": "法国菜",
			"duration": [
				[
					11,
					13.5
				],
				[
					17,
					21
				]
			],
			"tel": "17548405223",
			"distance": 7365,
			"video": "https://ak-v.tripcdn.com/videos/1A091t000001i1av39C52.mp4?ts=1622898856678"
		},
		"78":{
			"id": 78,
			"imgs": [
				"https://youimg1.c-ctrip.com/target/10030q000000goy0v1E89_D_750_562_Q90.jpg?proc=autoorient",
				"https://youimg1.c-ctrip.com/target/10090q000000gc0wr3753_D_750_562_Q90.jpg?proc=autoorient",
				"https://youimg1.c-ctrip.com/target/100l0q000000gndqr589A_D_750_562_Q90.jpg?proc=autoorient"
			],
			"name": "上面坊",
			"score": 4.5,
			"reviews": 676,
			"avgPrice": 603,
			"exactPosition": "卢湾区雁荡路14号",
			"generalPosition": "淮海路/新天地地区",
			"style": "面食",
			"duration": [
				[
					11,
					13.5
				],
				[
					17,
					21
				]
			],
			"tel": "13648474622",
			"distance": 9303,
			"video": "https://ak-v.tripcdn.com/videos/1A091t000001i1av39C52.mp4?ts=1622898856678"
		},
		"79":{
			"id": 79,
			"imgs": [
				"https://youimg1.c-ctrip.com/target/10030q000000goy0v1E89_D_750_562_Q90.jpg?proc=autoorient",
				"https://youimg1.c-ctrip.com/target/10090q000000gc0wr3753_D_750_562_Q90.jpg?proc=autoorient",
				"https://youimg1.c-ctrip.com/target/100l0q000000gndqr589A_D_750_562_Q90.jpg?proc=autoorient"
			],
			"name": "牛new寿喜烧",
			"score": 4.4,
			"reviews": 676,
			"avgPrice": 460,
			"exactPosition": "黄浦区淮海中路755号淮海755F3",
			"generalPosition": "淮海路/新天地地区",
			"style": "日式火锅",
			"duration": [
				[
					11,
					13.5
				],
				[
					17,
					21
				]
			],
			"tel": "15197123551",
			"distance": 7177,
			"video": "https://ak-v.tripcdn.com/videos/1A091t000001i1av39C52.mp4?ts=1622898856678"
		},
		"80":{
			"id": 80,
			"imgs": [
				"https://youimg1.c-ctrip.com/target/10030q000000goy0v1E89_D_750_562_Q90.jpg?proc=autoorient",
				"https://youimg1.c-ctrip.com/target/10090q000000gc0wr3753_D_750_562_Q90.jpg?proc=autoorient",
				"https://youimg1.c-ctrip.com/target/100l0q000000gndqr589A_D_750_562_Q90.jpg?proc=autoorient"
			],
			"name": "一緒に寿喜烧",
			"score": 3.2,
			"reviews": 698,
			"avgPrice": 391,
			"exactPosition": "静安区共和新路1878号大宁国际商业广场F4",
			"generalPosition": "淮海路/新天地地区",
			"style": "日式火锅",
			"duration": [
				[
					11,
					13.5
				],
				[
					17,
					21
				]
			],
			"tel": "17538933392",
			"distance": 4033,
			"video": "https://ak-v.tripcdn.com/videos/1A091t000001i1av39C52.mp4?ts=1622898856678"
		},
		"81":{
			"id": 81,
			"imgs": [
				"https://youimg1.c-ctrip.com/target/10030q000000goy0v1E89_D_750_562_Q90.jpg?proc=autoorient",
				"https://youimg1.c-ctrip.com/target/10090q000000gc0wr3753_D_750_562_Q90.jpg?proc=autoorient",
				"https://youimg1.c-ctrip.com/target/100l0q000000gndqr589A_D_750_562_Q90.jpg?proc=autoorient"
			],
			"name": "鑫花溪牛肉米粉",
			"score": 3.7,
			"reviews": 337,
			"avgPrice": 844,
			"exactPosition": "黄浦区人民大道9-99号67号店铺",
			"generalPosition": "淮海路/新天地地区",
			"style": "米粉/米线",
			"duration": [
				[
					11,
					13.5
				],
				[
					17,
					21
				]
			],
			"tel": "18835485655",
			"distance": 5185,
			"video": "https://ak-v.tripcdn.com/videos/1A091t000001i1av39C52.mp4?ts=1622898856678"
		},
		"82":{
			"id": 82,
			"imgs": [
				"https://youimg1.c-ctrip.com/target/10030q000000goy0v1E89_D_750_562_Q90.jpg?proc=autoorient",
				"https://youimg1.c-ctrip.com/target/10090q000000gc0wr3753_D_750_562_Q90.jpg?proc=autoorient",
				"https://youimg1.c-ctrip.com/target/100l0q000000gndqr589A_D_750_562_Q90.jpg?proc=autoorient"
			],
			"name": "小锄匠寿喜烧",
			"score": 3.2,
			"reviews": 37,
			"avgPrice": 145,
			"exactPosition": "浦东新区陆家嘴西路168号正大广场F8",
			"generalPosition": "淮海路/新天地地区",
			"style": "日式火锅",
			"duration": [
				[
					11,
					13.5
				],
				[
					17,
					21
				]
			],
			"tel": "14010782539",
			"distance": 1472,
			"video": "https://ak-v.tripcdn.com/videos/1A091t000001i1av39C52.mp4?ts=1622898856678"
		},
		"83":{
			"id": 83,
			"imgs": [
				"https://youimg1.c-ctrip.com/target/10030q000000goy0v1E89_D_750_562_Q90.jpg?proc=autoorient",
				"https://youimg1.c-ctrip.com/target/10090q000000gc0wr3753_D_750_562_Q90.jpg?proc=autoorient",
				"https://youimg1.c-ctrip.com/target/100l0q000000gndqr589A_D_750_562_Q90.jpg?proc=autoorient"
			],
			"name": "纽约客披萨",
			"score": 4.4,
			"reviews": 300,
			"avgPrice": 819,
			"exactPosition": "泰康路248弄田子坊23号甲",
			"generalPosition": "淮海路/新天地地区",
			"style": "披萨",
			"duration": [
				[
					11,
					13.5
				],
				[
					17,
					21
				]
			],
			"tel": "15530177136",
			"distance": 7018,
			"video": "https://ak-v.tripcdn.com/videos/1A091t000001i1av39C52.mp4?ts=1622898856678"
		},
		"84":{
			"id": 84,
			"imgs": [
				"https://youimg1.c-ctrip.com/target/10030q000000goy0v1E89_D_750_562_Q90.jpg?proc=autoorient",
				"https://youimg1.c-ctrip.com/target/10090q000000gc0wr3753_D_750_562_Q90.jpg?proc=autoorient",
				"https://youimg1.c-ctrip.com/target/100l0q000000gndqr589A_D_750_562_Q90.jpg?proc=autoorient"
			],
			"name": "南麓·浙里",
			"score": 4.6,
			"reviews": 331,
			"avgPrice": 979,
			"exactPosition": "中山东一路505号外滩18号7楼",
			"generalPosition": "淮海路/新天地地区",
			"style": "江浙菜",
			"duration": [
				[
					11,
					13.5
				],
				[
					17,
					21
				]
			],
			"tel": "15322887544",
			"distance": 2185,
			"video": "https://ak-v.tripcdn.com/videos/1A091t000001i1av39C52.mp4?ts=1622898856678"
		},
		"85":{
			"id": 85,
			"imgs": [
				"https://youimg1.c-ctrip.com/target/10030q000000goy0v1E89_D_750_562_Q90.jpg?proc=autoorient",
				"https://youimg1.c-ctrip.com/target/10090q000000gc0wr3753_D_750_562_Q90.jpg?proc=autoorient",
				"https://youimg1.c-ctrip.com/target/100l0q000000gndqr589A_D_750_562_Q90.jpg?proc=autoorient"
			],
			"name": "浦江荟",
			"score": 4.2,
			"reviews": 159,
			"avgPrice": 985,
			"exactPosition": "浦东新区滨江大道1850号A楼",
			"generalPosition": "淮海路/新天地地区",
			"style": "粤菜",
			"duration": [
				[
					11,
					13.5
				],
				[
					17,
					21
				]
			],
			"tel": "18774216444",
			"distance": 4092,
			"video": "https://ak-v.tripcdn.com/videos/1A091t000001i1av39C52.mp4?ts=1622898856678"
		},
		"86":{
			"id": 86,
			"imgs": [
				"https://youimg1.c-ctrip.com/target/10030q000000goy0v1E89_D_750_562_Q90.jpg?proc=autoorient",
				"https://youimg1.c-ctrip.com/target/10090q000000gc0wr3753_D_750_562_Q90.jpg?proc=autoorient",
				"https://youimg1.c-ctrip.com/target/100l0q000000gndqr589A_D_750_562_Q90.jpg?proc=autoorient"
			],
			"name": "唐宫",
			"score": 3.8,
			"reviews": 146,
			"avgPrice": 747,
			"exactPosition": "长宁区东诸安浜路103号维景酒店1~2楼",
			"generalPosition": "淮海路/新天地地区",
			"style": "粤菜",
			"duration": [
				[
					11,
					13.5
				],
				[
					17,
					21
				]
			],
			"tel": "14243513408",
			"distance": 6561,
			"video": "https://ak-v.tripcdn.com/videos/1A091t000001i1av39C52.mp4?ts=1622898856678"
		},
		"87":{
			"id": 87,
			"imgs": [
				"https://youimg1.c-ctrip.com/target/10030q000000goy0v1E89_D_750_562_Q90.jpg?proc=autoorient",
				"https://youimg1.c-ctrip.com/target/10090q000000gc0wr3753_D_750_562_Q90.jpg?proc=autoorient",
				"https://youimg1.c-ctrip.com/target/100l0q000000gndqr589A_D_750_562_Q90.jpg?proc=autoorient"
			],
			"name": "湖南乡村风味馆",
			"score": 4.6,
			"reviews": 482,
			"avgPrice": 756,
			"exactPosition": "徐汇区乌鲁木齐中路168号",
			"generalPosition": "淮海路/新天地地区",
			"style": "湘菜",
			"duration": [
				[
					11,
					13.5
				],
				[
					17,
					21
				]
			],
			"tel": "18582196858",
			"distance": 5389,
			"video": "https://ak-v.tripcdn.com/videos/1A091t000001i1av39C52.mp4?ts=1622898856678"
		},
		"88":{
			"id": 88,
			"imgs": [
				"https://youimg1.c-ctrip.com/target/10030q000000goy0v1E89_D_750_562_Q90.jpg?proc=autoorient",
				"https://youimg1.c-ctrip.com/target/10090q000000gc0wr3753_D_750_562_Q90.jpg?proc=autoorient",
				"https://youimg1.c-ctrip.com/target/100l0q000000gndqr589A_D_750_562_Q90.jpg?proc=autoorient"
			],
			"name": "寿司青",
			"score": 3.5,
			"reviews": 953,
			"avgPrice": 988,
			"exactPosition": "黄浦区南京东路228号新世界大丸百货B2",
			"generalPosition": "淮海路/新天地地区",
			"style": "寿司",
			"duration": [
				[
					11,
					13.5
				],
				[
					17,
					21
				]
			],
			"tel": "17272845290",
			"distance": 9018,
			"video": "https://ak-v.tripcdn.com/videos/1A091t000001i1av39C52.mp4?ts=1622898856678"
		},
		"89":{
			"id": 89,
			"imgs": [
				"https://youimg1.c-ctrip.com/target/10030q000000goy0v1E89_D_750_562_Q90.jpg?proc=autoorient",
				"https://youimg1.c-ctrip.com/target/10090q000000gc0wr3753_D_750_562_Q90.jpg?proc=autoorient",
				"https://youimg1.c-ctrip.com/target/100l0q000000gndqr589A_D_750_562_Q90.jpg?proc=autoorient"
			],
			"name": "永兴面馆",
			"score": 3.1,
			"reviews": 461,
			"avgPrice": 280,
			"exactPosition": "黄浦区广西北路452号",
			"generalPosition": "淮海路/新天地地区",
			"style": "面食",
			"duration": [
				[
					11,
					13.5
				],
				[
					17,
					21
				]
			],
			"tel": "18592112677",
			"distance": 3344,
			"video": "https://ak-v.tripcdn.com/videos/1A091t000001i1av39C52.mp4?ts=1622898856678"
		},
		"90":{
			"id": 90,
			"imgs": [
				"https://youimg1.c-ctrip.com/target/10030q000000goy0v1E89_D_750_562_Q90.jpg?proc=autoorient",
				"https://youimg1.c-ctrip.com/target/10090q000000gc0wr3753_D_750_562_Q90.jpg?proc=autoorient",
				"https://youimg1.c-ctrip.com/target/100l0q000000gndqr589A_D_750_562_Q90.jpg?proc=autoorient"
			],
			"name": "小芳廷",
			"score": 4.7,
			"reviews": 975,
			"avgPrice": 598,
			"exactPosition": "普陀区长寿路652号国际教育中心k栋",
			"generalPosition": "淮海路/新天地地区",
			"style": "意大利菜",
			"duration": [
				[
					11,
					13.5
				],
				[
					17,
					21
				]
			],
			"tel": "17377254726",
			"distance": 7832,
			"video": "https://ak-v.tripcdn.com/videos/1A091t000001i1av39C52.mp4?ts=1622898856678"
		},
		"91":{
			"id": 91,
			"imgs": [
				"https://youimg1.c-ctrip.com/target/10030q000000goy0v1E89_D_750_562_Q90.jpg?proc=autoorient",
				"https://youimg1.c-ctrip.com/target/10090q000000gc0wr3753_D_750_562_Q90.jpg?proc=autoorient",
				"https://youimg1.c-ctrip.com/target/100l0q000000gndqr589A_D_750_562_Q90.jpg?proc=autoorient"
			],
			"name": "小杨生煎(愚园路店)",
			"score": 3.2,
			"reviews": 577,
			"avgPrice": 935,
			"exactPosition": "上海市长宁区愚园路816弄",
			"generalPosition": "淮海路/新天地地区",
			"style": "中式快餐",
			"duration": [
				[
					11,
					13.5
				],
				[
					17,
					21
				]
			],
			"tel": "15005317156",
			"distance": 6815,
			"video": "https://ak-v.tripcdn.com/videos/1A091t000001i1av39C52.mp4?ts=1622898856678"
		},
		"92":{
			"id": 92,
			"imgs": [
				"https://youimg1.c-ctrip.com/target/10030q000000goy0v1E89_D_750_562_Q90.jpg?proc=autoorient",
				"https://youimg1.c-ctrip.com/target/10090q000000gc0wr3753_D_750_562_Q90.jpg?proc=autoorient",
				"https://youimg1.c-ctrip.com/target/100l0q000000gndqr589A_D_750_562_Q90.jpg?proc=autoorient"
			],
			"name": "寿司沼津港)",
			"score": 3.4,
			"reviews": 192,
			"avgPrice": 152,
			"exactPosition": "静安区恒通路318号凯德星贸2楼-07(汉中路)",
			"generalPosition": "淮海路/新天地地区",
			"style": "寿司",
			"duration": [
				[
					11,
					13.5
				],
				[
					17,
					21
				]
			],
			"tel": "15601549728",
			"distance": 8510,
			"video": "https://ak-v.tripcdn.com/videos/1A091t000001i1av39C52.mp4?ts=1622898856678"
		},
		"93":{
			"id": 93,
			"imgs": [
				"https://youimg1.c-ctrip.com/target/10030q000000goy0v1E89_D_750_562_Q90.jpg?proc=autoorient",
				"https://youimg1.c-ctrip.com/target/10090q000000gc0wr3753_D_750_562_Q90.jpg?proc=autoorient",
				"https://youimg1.c-ctrip.com/target/100l0q000000gndqr589A_D_750_562_Q90.jpg?proc=autoorient"
			],
			"name": "杨国福麻辣烫",
			"score": 3.4,
			"reviews": 254,
			"avgPrice": 439,
			"exactPosition": "杨浦区政旦东路40号",
			"generalPosition": "淮海路/新天地地区",
			"style": "麻辣烫",
			"duration": [
				[
					11,
					13.5
				],
				[
					17,
					21
				]
			],
			"tel": "14629168328",
			"distance": 4445,
			"video": "https://ak-v.tripcdn.com/videos/1A091t000001i1av39C52.mp4?ts=1622898856678"
		},
		"94":{
			"id": 94,
			"imgs": [
				"https://youimg1.c-ctrip.com/target/10030q000000goy0v1E89_D_750_562_Q90.jpg?proc=autoorient",
				"https://youimg1.c-ctrip.com/target/10090q000000gc0wr3753_D_750_562_Q90.jpg?proc=autoorient",
				"https://youimg1.c-ctrip.com/target/100l0q000000gndqr589A_D_750_562_Q90.jpg?proc=autoorient"
			],
			"name": "红房子西菜馆",
			"score": 4.2,
			"reviews": 530,
			"avgPrice": 938,
			"exactPosition": "黄浦区淮海中路845号",
			"generalPosition": "淮海路/新天地地区",
			"style": "法国菜",
			"duration": [
				[
					11,
					13.5
				],
				[
					17,
					21
				]
			],
			"tel": "17522497673",
			"distance": 7076,
			"video": "https://ak-v.tripcdn.com/videos/1A091t000001i1av39C52.mp4?ts=1622898856678"
		},
		"95":{
			"id": 95,
			"imgs": [
				"https://youimg1.c-ctrip.com/target/10030q000000goy0v1E89_D_750_562_Q90.jpg?proc=autoorient",
				"https://youimg1.c-ctrip.com/target/10090q000000gc0wr3753_D_750_562_Q90.jpg?proc=autoorient",
				"https://youimg1.c-ctrip.com/target/100l0q000000gndqr589A_D_750_562_Q90.jpg?proc=autoorient"
			],
			"name": "云庐(陆家嘴店)",
			"score": 4.2,
			"reviews": 251,
			"avgPrice": 880,
			"exactPosition": "浦东新区陆家嘴环路166号正大广场8楼",
			"generalPosition": "淮海路/新天地地区",
			"style": "江浙菜",
			"duration": [
				[
					11,
					13.5
				],
				[
					17,
					21
				]
			],
			"tel": "18288048822",
			"distance": 4740,
			"video": "https://ak-v.tripcdn.com/videos/1A091t000001i1av39C52.mp4?ts=1622898856678"
		},
		"96":{
			"id": 96,
			"imgs": [
				"https://youimg1.c-ctrip.com/target/10030q000000goy0v1E89_D_750_562_Q90.jpg?proc=autoorient",
				"https://youimg1.c-ctrip.com/target/10090q000000gc0wr3753_D_750_562_Q90.jpg?proc=autoorient",
				"https://youimg1.c-ctrip.com/target/100l0q000000gndqr589A_D_750_562_Q90.jpg?proc=autoorient"
			],
			"name": "金湘隆·清派湘菜",
			"score": 3.9,
			"reviews": 966,
			"avgPrice": 852,
			"exactPosition": "嘉定区新源路602号",
			"generalPosition": "淮海路/新天地地区",
			"style": "湘菜",
			"duration": [
				[
					11,
					13.5
				],
				[
					17,
					21
				]
			],
			"tel": "15193221381",
			"distance": 5035,
			"video": "https://ak-v.tripcdn.com/videos/1A091t000001i1av39C52.mp4?ts=1622898856678"
		},
		"97":{
			"id": 97,
			"imgs": [
				"https://youimg1.c-ctrip.com/target/10030q000000goy0v1E89_D_750_562_Q90.jpg?proc=autoorient",
				"https://youimg1.c-ctrip.com/target/10090q000000gc0wr3753_D_750_562_Q90.jpg?proc=autoorient",
				"https://youimg1.c-ctrip.com/target/100l0q000000gndqr589A_D_750_562_Q90.jpg?proc=autoorient"
			],
			"name": "海世轩公馆",
			"score": 4.3,
			"reviews": 266,
			"avgPrice": 663,
			"exactPosition": "长宁区法华镇路218号",
			"generalPosition": "淮海路/新天地地区",
			"style": "粤菜",
			"duration": [
				[
					11,
					13.5
				],
				[
					17,
					21
				]
			],
			"tel": "14268797406",
			"distance": 6487,
			"video": "https://ak-v.tripcdn.com/videos/1A091t000001i1av39C52.mp4?ts=1622898856678"
		},
		"98":{
			"id": 98,
			"imgs": [
				"https://youimg1.c-ctrip.com/target/10030q000000goy0v1E89_D_750_562_Q90.jpg?proc=autoorient",
				"https://youimg1.c-ctrip.com/target/10090q000000gc0wr3753_D_750_562_Q90.jpg?proc=autoorient",
				"https://youimg1.c-ctrip.com/target/100l0q000000gndqr589A_D_750_562_Q90.jpg?proc=autoorient"
			],
			"name": "惠食佳",
			"score": 3.4,
			"reviews": 110,
			"avgPrice": 603,
			"exactPosition": "静安区延安西路396号美丽园大酒店3层",
			"generalPosition": "淮海路/新天地地区",
			"style": "粤菜",
			"duration": [
				[
					11,
					13.5
				],
				[
					17,
					21
				]
			],
			"tel": "17786191665",
			"distance": 2414,
			"video": "https://ak-v.tripcdn.com/videos/1A091t000001i1av39C52.mp4?ts=1622898856678"
		},
		"99":{
			"id": 99,
			"imgs": [
				"https://youimg1.c-ctrip.com/target/10030q000000goy0v1E89_D_750_562_Q90.jpg?proc=autoorient",
				"https://youimg1.c-ctrip.com/target/10090q000000gc0wr3753_D_750_562_Q90.jpg?proc=autoorient",
				"https://youimg1.c-ctrip.com/target/100l0q000000gndqr589A_D_750_562_Q90.jpg?proc=autoorient"
			],
			"name": "久久滴水洞湘菜馆",
			"score": 3.4,
			"reviews": 977,
			"avgPrice": 741,
			"exactPosition": "黄浦区茂名南路56号久久滴水洞茂名店2层",
			"generalPosition": "淮海路/新天地地区",
			"style": "湘菜",
			"duration": [
				[
					11,
					13.5
				],
				[
					17,
					21
				]
			],
			"tel": "19528346633",
			"distance": 9940,
			"video": "https://ak-v.tripcdn.com/videos/1A091t000001i1av39C52.mp4?ts=1622898856678"
		},
		"100":{
			"id": 100,
			"imgs": [
				"https://youimg1.c-ctrip.com/target/10030q000000goy0v1E89_D_750_562_Q90.jpg?proc=autoorient",
				"https://youimg1.c-ctrip.com/target/10090q000000gc0wr3753_D_750_562_Q90.jpg?proc=autoorient",
				"https://youimg1.c-ctrip.com/target/100l0q000000gndqr589A_D_750_562_Q90.jpg?proc=autoorient"
			],
			"name": "Solo",
			"score": 4.2,
			"reviews": 441,
			"avgPrice": 272,
			"exactPosition": "徐汇区天平路街道衡山路191号103",
			"generalPosition": "淮海路/新天地地区",
			"style": "意大利菜",
			"duration": [
				[
					11,
					13.5
				],
				[
					17,
					21
				]
			],
			"tel": "14576255721",
			"distance": 7752,
			"video": "https://ak-v.tripcdn.com/videos/1A091t000001i1av39C52.mp4?ts=1622898856678"
		}
    "data": {
        "1":{
            "id": 1,
            "imgs": [
                "https://ak-v.tripcdn.com/videos/1A091t000001i1av39C52.mp4?ts=1622898856678",
                "https://youimg1.c-ctrip.com/target/10030q000000goy0v1E89_D_750_562_Q90.jpg?proc=autoorient",
                "https://youimg1.c-ctrip.com/target/10090q000000gc0wr3753_D_750_562_Q90.jpg?proc=autoorient",
                "https://youimg1.c-ctrip.com/target/100l0q000000gndqr589A_D_750_562_Q90.jpg?proc=autoorient"
            ],
            "name": "甬府（黄浦店）",
            "score": 4.7,
            "reviews": 12340,
            "avgPrice": 964,
            "exactPosition": "茂名南路59号锦江饭店锦北楼12层(近长乐路)距地铁1号线陕西南路站(3口)467m，步行6min",
            "generalPosition": "淮海路/新天地地区",
            "style": "江浙菜",
            "duration": [
                [
                    11,
                    13.5
                ],
                [
                    17,
                    21
                ]
            ],
            "tel": "13327220630",
            "video": ""
        },
        "2":{
            "id": 2,
            "imgs": [
                "https://youimg1.c-ctrip.com/target/10030q000000goy0v1E89_D_750_562_Q90.jpg?proc=autoorient",
                "https://youimg1.c-ctrip.com/target/10090q000000gc0wr3753_D_750_562_Q90.jpg?proc=autoorient",
                "https://youimg1.c-ctrip.com/target/100l0q000000gndqr589A_D_750_562_Q90.jpg?proc=autoorient"
            ],
            "name": "甬府（黄浦店）",
            "score": 4.7,
            "reviews": 12340,
            "avgPrice": 964,
            "exactPosition": "茂名南路59号锦江饭店锦北楼12层(近长乐路)距地铁1号线陕西南路站(3口)467m，步行6min",
            "generalPosition": "淮海路/新天地地区",
            "style": "江浙菜",
            "duration": [
                [
                    11,
                    13.5
                ],
                [
                    17,
                    21
                ]
            ],
            "tel": "13327220630",
            "video": ""
        },
        "3":{
            "id": 3,
            "imgs": [
                "https://youimg1.c-ctrip.com/target/10030q000000goy0v1E89_D_750_562_Q90.jpg?proc=autoorient",
                "https://youimg1.c-ctrip.com/target/10090q000000gc0wr3753_D_750_562_Q90.jpg?proc=autoorient",
                "https://youimg1.c-ctrip.com/target/100l0q000000gndqr589A_D_750_562_Q90.jpg?proc=autoorient"
            ],
            "name": "甬府（黄浦店）",
            "score": 4.7,
            "reviews": 12340,
            "avgPrice": 964,
            "exactPosition": "茂名南路59号锦江饭店锦北楼12层(近长乐路)距地铁1号线陕西南路站(3口)467m，步行6min",
            "generalPosition": "淮海路/新天地地区",
            "style": "江浙菜",
            "duration": [
                [
                    11,
                    13.5
                ],
                [
                    17,
                    21
                ]
            ],
            "tel": "13327220630",
            "video": ""
        },
        "4":{
            "id": 4,
            "imgs": [
                "https://youimg1.c-ctrip.com/target/10030q000000goy0v1E89_D_750_562_Q90.jpg?proc=autoorient",
                "https://youimg1.c-ctrip.com/target/10090q000000gc0wr3753_D_750_562_Q90.jpg?proc=autoorient",
                "https://youimg1.c-ctrip.com/target/100l0q000000gndqr589A_D_750_562_Q90.jpg?proc=autoorient"
            ],
            "name": "甬府（黄浦店）",
            "score": 4.7,
            "reviews": 12340,
            "avgPrice": 964,
            "exactPosition": "茂名南路59号锦江饭店锦北楼12层(近长乐路)距地铁1号线陕西南路站(3口)467m，步行6min",
            "generalPosition": "淮海路/新天地地区",
            "style": "江浙菜",
            "duration": [
                [
                    11,
                    13.5
                ],
                [
                    17,
                    21
                ]
            ],
            "tel": "13327220630",
            "video": ""
        },
        "5":{
            "id": 5,
            "imgs": [
                "https://youimg1.c-ctrip.com/target/10030q000000goy0v1E89_D_750_562_Q90.jpg?proc=autoorient",
                "https://youimg1.c-ctrip.com/target/10090q000000gc0wr3753_D_750_562_Q90.jpg?proc=autoorient",
                "https://youimg1.c-ctrip.com/target/100l0q000000gndqr589A_D_750_562_Q90.jpg?proc=autoorient"
            ],
            "name": "甬府（黄浦店）",
            "score": 4.7,
            "reviews": 12340,
            "avgPrice": 964,
            "exactPosition": "茂名南路59号锦江饭店锦北楼12层(近长乐路)距地铁1号线陕西南路站(3口)467m，步行6min",
            "generalPosition": "淮海路/新天地地区",
            "style": "江浙菜",
            "duration": [
                [
                    11,
                    13.5
                ],
                [
                    17,
                    21
                ]
            ],
            "tel": "13327220630",
            "video": ""
        },
        "6":{
            "id": 6,
            "imgs": [
                "https://youimg1.c-ctrip.com/target/10030q000000goy0v1E89_D_750_562_Q90.jpg?proc=autoorient",
                "https://youimg1.c-ctrip.com/target/10090q000000gc0wr3753_D_750_562_Q90.jpg?proc=autoorient",
                "https://youimg1.c-ctrip.com/target/100l0q000000gndqr589A_D_750_562_Q90.jpg?proc=autoorient"
            ],
            "name": "甬府（黄浦店）",
            "score": 4.7,
            "reviews": 12340,
            "avgPrice": 964,
            "exactPosition": "茂名南路59号锦江饭店锦北楼12层(近长乐路)距地铁1号线陕西南路站(3口)467m，步行6min",
            "generalPosition": "淮海路/新天地地区",
            "style": "江浙菜",
            "duration": [
                [
                    11,
                    13.5
                ],
                [
                    17,
                    21
                ]
            ],
            "tel": "13327220630",
            "video": ""
        },
        "7":{
            "id": 7,
            "imgs": [
                "https://youimg1.c-ctrip.com/target/10030q000000goy0v1E89_D_750_562_Q90.jpg?proc=autoorient",
                "https://youimg1.c-ctrip.com/target/10090q000000gc0wr3753_D_750_562_Q90.jpg?proc=autoorient",
                "https://youimg1.c-ctrip.com/target/100l0q000000gndqr589A_D_750_562_Q90.jpg?proc=autoorient"
            ],
            "name": "甬府（黄浦店）",
            "score": 4.7,
            "reviews": 12340,
            "avgPrice": 964,
            "exactPosition": "茂名南路59号锦江饭店锦北楼12层(近长乐路)距地铁1号线陕西南路站(3口)467m，步行6min",
            "generalPosition": "淮海路/新天地地区",
            "style": "江浙菜",
            "duration": [
                [
                    11,
                    13.5
                ],
                [
                    17,
                    21
                ]
            ],
            "tel": "13327220630",
            "video": ""
        }
    }
}